{
  "errors": [],
  "results": [
    {
      "categoryId": 1,
      "cleanName": "From the Vault Annihilation Box Set",
      "extendedData": [
        {
          "displayName": "Rules Text Contains",
          "name": "OracleText",
          "value": "Each From the Vault: Annihilation - Box Set contains 15 premium foil cards."
        }
      ],
      "groupId": 1475,
      "imageCount": 1,
      "imageUrl": "https://tcgplayer-cdn.tcgplayer.com/product/91636_200w.jpg",
      "modifiedOn": "2020-01-06T20:17:20.01",
      "name": "From the Vault: Annihilation - Box Set",
      "presaleInfo": {
        "isPresale": false,
        "note": null,
        "releasedOn": null
      },
      "productId": 91636,
      "url": "https://www.tcgplayer.com/product/91636/magic-from-the-vault-annihilation-from-the-vault-annihilation-box-set"
    },
    {
      "categoryId": 1,
      "cleanName": "Armageddon",
      "extendedData": [
        {
          "displayName": "Rarity",
          "name": "Rarity",
          "value": "M"
        },
        {
          "displayName": "#",
          "name": "Number",
          "value": "1"
        },
        {
          "displayName": "Creature Type or Sub Type",
          "name": "SubType",
          "value": "Sorcery"
        },
        {
          "displayName": "Rules Text Contains",
          "name": "OracleText",
          "value": "Destroy all lands"
        },
        {
          "displayName": "Flavor",
          "name": "FlavorText",
          "value": "\u003cem\u003eA bloody dawn broke over a scabbed and tortured world.\u003c/em\u003e"
        }
      ],
      "groupId": 1475,
      "imageCount": 1,
      "imageUrl": "https://tcgplayer-cdn.tcgplayer.com/product/91637_200w.jpg",
      "modifiedOn": "2025-12-08T13:44:15.79",
      "name": "Armageddon",
      "presaleInfo": {
        "isPresale": false,
        "note": null,
        "releasedOn": null
      },
      "productId": 91637,
      "url": "https://www.tcgplayer.com/product/91637/magic-from-the-vault-annihilation-armageddon"
    },
    {
      "categoryId": 1,
      "cleanName": "Cataclysm",
      "extendedData": [
        {
          "displayName": "Rarity",
          "name": "Rarity",
          "value": "M"
        },
        {
          "displayName": "#",
          "name": "Number",
          "value": "3"
        },
        {
          "displayName": "Creature Type or Sub Type",
          "name": "SubType",
          "value": "Sorcery"
        },
        {
          "displayName": "Rules Text Contains",
          "name": "OracleText",
          "value": "Each player chooses from among the permanents he or she controls an artifact, a creature, an enchantment, and a land, then sacrifices the rest."
        },
        {
          "displayName": "Flavor",
          "name": "FlavorText",
          "value": "\u003cem\u003e“Keep with you only this much: your mount, your blade, and your wits. The rest you can find, build, or take.”\r\n\u003cbr\u003e\r\n—Horse clans’ wisdom\u003c/em\u003e"
        }
      ],
      "groupId": 1475,
      "imageCount": 1,
      "imageUrl": "https://tcgplayer-cdn.tcgplayer.com/product/91638_200w.jpg",
      "modifiedOn": "2025-05-01T14:10:15.227",
      "name": "Cataclysm",
      "presaleInfo": {
        "isPresale": false,
        "note": null,
        "releasedOn": null
      },
      "productId": 91638,
      "url": "https://www.tcgplayer.com/product/91638/magic-from-the-vault-annihilation-cataclysm"
    },
    {
      "categoryId": 1,
      "cleanName": "Living Death",
      "extendedData": [
        {
          "displayName": "Rarity",
          "name": "Rarity",
          "value": "M"
        },
        {
          "displayName": "#",
          "name": "Number",
          "value": "8"
        },
        {
          "displayName": "Creature Type or Sub Type",
          "name": "SubType",
          "value": "Sorcery"
        },
        {
          "displayName": "Rules Text Contains",
          "name": "OracleText",
          "value": "Each player exiles all creature cards from his or her graveyard, then sacrifices all creatures he or she controls, the puts all cards he or she exiled this way onto the battlefield."
        }
      ],
      "groupId": 1475,
      "imageCount": 1,
      "imageUrl": "https://tcgplayer-cdn.tcgplayer.com/product/91639_200w.jpg",
      "modifiedOn": "2025-05-01T14:15:57.753",
      "name": "Living Death",
      "presaleInfo": {
        "isPresale": false,
        "note": null,
        "releasedOn": null
      },
      "productId": 91639,
      "url": "https://www.tcgplayer.com/product/91639/magic-from-the-vault-annihilation-living-death"
    },
    {
      "categoryId": 1,
      "cleanName": "Rolling Earthquake",
      "extendedData": [
        {
          "displayName": "Rarity",
          "name": "Rarity",
          "value": "M"
        },
        {
          "displayName": "#",
          "name": "Number",
          "value": "10"
        },
        {
          "displayName": "Creature Type or Sub Type",
          "name": "SubType",
          "value": "Sorcery"
        },
        {
          "displayName": "Rules Text Contains",
          "name": "OracleText",
          "value": "Rolling Earthquake deals X damage to each creature without horsemanship and each player."
        }
      ],
      "groupId": 1475,
      "imageCount": 1,
      "imageUrl": "https://tcgplayer-cdn.tcgplayer.com/product/91640_200w.jpg",
      "modifiedOn": "2025-05-01T14:16:38.823",
      "name": "Rolling Earthquake",
      "presaleInfo": {
        "isPresale": false,
        "note": null,
        "releasedOn": null
      },
      "productId": 91640,
      "url": "https://www.tcgplayer.com/product/91640/magic-from-the-vault-annihilation-rolling-earthquake"
    },
    {
      "categoryId": 1,
      "cleanName": "Wrath of God",
      "extendedData": [
        {
          "displayName": "Rarity",
          "name": "Rarity",
          "value": "M"
        },
        {
          "displayName": "#",
          "name": "Number",
          "value": "15"
        },
        {
          "displayName": "Creature Type or Sub Type",
          "name": "SubType",
          "value": "Sorcery"
        },
        {
          "displayName": "Rules Text Contains",
          "name": "OracleText",
          "value": "Destroy all creatures. They can't be regenerated."
        },
        {
          "displayName": "Flavor",
          "name": "FlavorText",
          "value": "\u003cem\u003eLegend speaks of the lost coastal polis of Olantin, whose inhabitants' hubris enraged the sun gold Heliod.\u003c/em\u003e"
        }
      ],
      "groupId": 1475,
      "imageCount": 1,
      "imageUrl": "https://tcgplayer-cdn.tcgplayer.com/product/91641_200w.jpg",
      "modifiedOn": "2025-05-01T14:23:46.803",
      "name": "Wrath of God",
      "presaleInfo": {
        "isPresale": false,
        "note": null,
        "releasedOn": null
      },
      "productId": 91641,
      "url": "https://www.tcgplayer.com/product/91641/magic-from-the-vault-annihilation-wrath-of-god"
    },
    {
      "categoryId": 1,
      "cleanName": "Burning of Xinye",
      "extendedData": [
        {
          "displayName": "Rarity",
          "name": "Rarity",
          "value": "M"
        },
        {
          "displayName": "#",
          "name": "Number",
          "value": "2"
        },
        {
          "displayName": "Creature Type or Sub Type",
          "name": "SubType",
          "value": "Sorcery"
        },
        {
          "displayName": "Rules Text Contains",
          "name": "OracleText",
          "value": "You destroy four lands you control, then target opponent destroys four lands he or she controls. Then Burning of Xinye deals 4 damage to each creature."
        }
      ],
      "groupId": 1475,
      "imageCount": 1,
      "imageUrl": "https://tcgplayer-cdn.tcgplayer.com/product/92296_200w.jpg",
      "modifiedOn": "2025-05-01T13:58:31.78",
      "name": "Burning of Xinye",
      "presaleInfo": {
        "isPresale": false,
        "note": null,
        "releasedOn": null
      },
      "productId": 92296,
      "url": "https://www.tcgplayer.com/product/92296/magic-from-the-vault-annihilation-burning-of-xinye"
    },
    {
      "categoryId": 1,
      "cleanName": "Child of Alara",
      "extendedData": [
        {
          "displayName": "Rarity",
          "name": "Rarity",
          "value": "M"
        },
        {
          "displayName": "#",
          "name": "Number",
          "value": "4"
        },
        {
          "displayName": "Creature Type or Sub Type",
          "name": "SubType",
          "value": "Legendary Creature — Avatar"
        },
        {
          "displayName": "P",
          "name": "P",
          "value": "6"
        },
        {
          "displayName": "T",
          "name": "T",
          "value": "6"
        },
        {
          "displayName": "Rules Text Contains",
          "name": "OracleText",
          "value": "Trample \r\n\u003cbr\u003e\r\nWhen Child of Alara dies, destroy all nonland permanents. They can't be regenerated."
        },
        {
          "displayName": "Flavor",
          "name": "FlavorText",
          "value": "\u003cem\u003eThe progeny of the Maelstrom shows no allegiance—and no mercy—to any of the five shards.\u003c/em\u003e"
        }
      ],
      "groupId": 1475,
      "imageCount": 1,
      "imageUrl": "https://tcgplayer-cdn.tcgplayer.com/product/92297_200w.jpg",
      "modifiedOn": "2025-05-01T14:11:00.253",
      "name": "Child of Alara",
      "presaleInfo": {
        "isPresale": false,
        "note": null,
        "releasedOn": null
      },
      "productId": 92297,
      "url": "https://www.tcgplayer.com/product/92297/magic-from-the-vault-annihilation-child-of-alara"
    },
    {
      "categoryId": 1,
      "cleanName": "Decree of Annihilation",
      "extendedData": [
        {
          "displayName": "Rarity",
          "name": "Rarity",
          "value": "M"
        },
        {
          "displayName": "#",
          "name": "Number",
          "value": "5"
        },
        {
          "displayName": "Creature Type or Sub Type",
          "name": "SubType",
          "value": "Sorcery"
        },
        {
          "displayName": "Rules Text Contains",
          "name": "OracleText",
          "value": "Exile all artifacts, creatures, and lands from the battlefield, all cards from all graveyards, and all cards from all hands.\r\n\u003cbr\u003e\r\nCycling 5RR \u003cem\u003e(5RR, Discard this card: Draw a card.)\u003c/em\u003e\r\n\u003cbr\u003e\r\nWhen you cycle Decree of Annihilation, destroy all lands."
        }
      ],
      "groupId": 1475,
      "imageCount": 1,
      "imageUrl": "https://tcgplayer-cdn.tcgplayer.com/product/92298_200w.jpg",
      "modifiedOn": "2025-05-01T14:12:26.837",
      "name": "Decree of Annihilation",
      "presaleInfo": {
        "isPresale": false,
        "note": null,
        "releasedOn": null
      },
      "productId": 92298,
      "url": "https://www.tcgplayer.com/product/92298/magic-from-the-vault-annihilation-decree-of-annihilation"
    },
    {
      "categoryId": 1,
      "cleanName": "Martial Coup",
      "extendedData": [
        {
          "displayName": "Rarity",
          "name": "Rarity",
          "value": "M"
        },
        {
          "displayName": "#",
          "name": "Number",
          "value": "9"
        },
        {
          "displayName": "Creature Type or Sub Type",
          "name": "SubType",
          "value": "Sorcery"
        },
        {
          "displayName": "Rules Text Contains",
          "name": "OracleText",
          "value": "Put X 1/1 white Soldier creature tokens into play. If X is 5 or more, destroy all other creatures."
        },
        {
          "displayName": "Flavor",
          "name": "FlavorText",
          "value": "\u003cem\u003eTheir war forgotten, the nations of Bant stood united in the face of a common threat.\u003c/em\u003e"
        }
      ],
      "groupId": 1475,
      "imageCount": 1,
      "imageUrl": "https://tcgplayer-cdn.tcgplayer.com/product/92299_200w.jpg",
      "modifiedOn": "2025-05-01T14:16:15.113",
      "name": "Martial Coup",
      "presaleInfo": {
        "isPresale": false,
        "note": null,
        "releasedOn": null
      },
      "productId": 92299,
      "url": "https://www.tcgplayer.com/product/92299/magic-from-the-vault-annihilation-martial-coup"
    },
    {
      "categoryId": 1,
      "cleanName": "Firespout",
      "extendedData": [
        {
          "displayName": "Rarity",
          "name": "Rarity",
          "value": "M"
        },
        {
          "displayName": "#",
          "name": "Number",
          "value": "6"
        },
        {
          "displayName": "Creature Type or Sub Type",
          "name": "SubType",
          "value": "Sorcery"
        },
        {
          "displayName": "Rules Text Contains",
          "name": "OracleText",
          "value": "Firespout deals 3 damage to each creature without flying if R was spent to cast Firespout and 3 damage to each creature with flying if G was spent to cast it. \u003cem\u003e(Do both if RG was spent.)\u003c/em\u003e"
        }
      ],
      "groupId": 1475,
      "imageCount": 1,
      "imageUrl": "https://tcgplayer-cdn.tcgplayer.com/product/92300_200w.jpg",
      "modifiedOn": "2025-05-01T14:13:27.167",
      "name": "Firespout",
      "presaleInfo": {
        "isPresale": false,
        "note": null,
        "releasedOn": null
      },
      "productId": 92300,
      "url": "https://www.tcgplayer.com/product/92300/magic-from-the-vault-annihilation-firespout"
    },
    {
      "categoryId": 1,
      "cleanName": "Fracturing Gust",
      "extendedData": [
        {
          "displayName": "Rarity",
          "name": "Rarity",
          "value": "M"
        },
        {
          "displayName": "#",
          "name": "Number",
          "value": "7"
        },
        {
          "displayName": "Creature Type or Sub Type",
          "name": "SubType",
          "value": "Instant"
        },
        {
          "displayName": "Rules Text Contains",
          "name": "OracleText",
          "value": "Destroy all artifacts and enchantments. You gain 2 life for each permanent destroyed this way."
        },
        {
          "displayName": "Flavor",
          "name": "FlavorText",
          "value": "\u003cem\u003eElvish dawnhands test a relic's worthiness before collecting it for the safehold. If it can't stand up to a stiff breeze, it's left behind.\u003c/em\u003e"
        }
      ],
      "groupId": 1475,
      "imageCount": 1,
      "imageUrl": "https://tcgplayer-cdn.tcgplayer.com/product/92301_200w.jpg",
      "modifiedOn": "2023-12-02T11:46:09.073",
      "name": "Fracturing Gust",
      "presaleInfo": {
        "isPresale": false,
        "note": null,
        "releasedOn": null
      },
      "productId": 92301,
      "url": "https://www.tcgplayer.com/product/92301/magic-from-the-vault-annihilation-fracturing-gust"
    },
    {
      "categoryId": 1,
      "cleanName": "Smokestack",
      "extendedData": [
        {
          "displayName": "Rarity",
          "name": "Rarity",
          "value": "M"
        },
        {
          "displayName": "#",
          "name": "Number",
          "value": "11"
        },
        {
          "displayName": "Creature Type or Sub Type",
          "name": "SubType",
          "value": "Artifact"
        },
        {
          "displayName": "Rules Text Contains",
          "name": "OracleText",
          "value": "At the beginning of your upkeep, you may put a soot counter on Smokestack.\r\n\u003cbr\u003e\r\nAt the beginning of each player’s upkeep, that player sacrifices a permanent for each soot counter on Smokestack."
        }
      ],
      "groupId": 1475,
      "imageCount": 1,
      "imageUrl": "https://tcgplayer-cdn.tcgplayer.com/product/92302_200w.jpg",
      "modifiedOn": "2025-05-01T14:19:25.04",
      "name": "Smokestack",
      "presaleInfo": {
        "isPresale": false,
        "note": null,
        "releasedOn": null
      },
      "productId": 92302,
      "url": "https://www.tcgplayer.com/product/92302/magic-from-the-vault-annihilation-smokestack"
    },
    {
      "categoryId": 1,
      "cleanName": "Terminus",
      "extendedData": [
        {
          "displayName": "Rarity",
          "name": "Rarity",
          "value": "M"
        },
        {
          "displayName": "#",
          "name": "Number",
          "value": "12"
        },
        {
          "displayName": "Creature Type or Sub Type",
          "name": "SubType",
          "value": "Sorcery"
        },
        {
          "displayName": "Rules Text Contains",
          "name": "OracleText",
          "value": "Put all creatures on the bottom of their owners' libraries.\r\n\u003cbr\u003e\r\nMiracle W \u003cem\u003e(You may cast this card for its miracle cost when you draw it if it's the first card you drew this turn.)\u003c/em\u003e"
        }
      ],
      "groupId": 1475,
      "imageCount": 1,
      "imageUrl": "https://tcgplayer-cdn.tcgplayer.com/product/92303_200w.jpg",
      "modifiedOn": "2025-05-01T14:22:11.353",
      "name": "Terminus",
      "presaleInfo": {
        "isPresale": false,
        "note": null,
        "releasedOn": null
      },
      "productId": 92303,
      "url": "https://www.tcgplayer.com/product/92303/magic-from-the-vault-annihilation-terminus"
    },
    {
      "categoryId": 1,
      "cleanName": "Upheaval",
      "extendedData": [
        {
          "displayName": "Rarity",
          "name": "Rarity",
          "value": "M"
        },
        {
          "displayName": "#",
          "name": "Number",
          "value": "13"
        },
        {
          "displayName": "Creature Type or Sub Type",
          "name": "SubType",
          "value": "Sorcery"
        },
        {
          "displayName": "Rules Text Contains",
          "name": "OracleText",
          "value": "Return all permanents to their owners` hands."
        },
        {
          "displayName": "Flavor",
          "name": "FlavorText",
          "value": "\u003cem\u003eThe calm comes after the storm.\u003c/em\u003e"
        }
      ],
      "groupId": 1475,
      "imageCount": 1,
      "imageUrl": "https://tcgplayer-cdn.tcgplayer.com/product/92304_200w.jpg",
      "modifiedOn": "2020-01-06T21:04:54.277",
      "name": "Upheaval",
      "presaleInfo": {
        "isPresale": false,
        "note": null,
        "releasedOn": null
      },
      "productId": 92304,
      "url": "https://www.tcgplayer.com/product/92304/magic-from-the-vault-annihilation-upheaval"
    },
    {
      "categoryId": 1,
      "cleanName": "Virtues Ruin",
      "extendedData": [
        {
          "displayName": "Rarity",
          "name": "Rarity",
          "value": "M"
        },
        {
          "displayName": "#",
          "name": "Number",
          "value": "14"
        },
        {
          "displayName": "Creature Type or Sub Type",
          "name": "SubType",
          "value": "Sorcery"
        },
        {
          "displayName": "Rules Text Contains",
          "name": "OracleText",
          "value": "Destroy all white creatures.\u003cem\u003e (This includes your white creatures.)\u003c/em\u003e"
        },
        {
          "displayName": "Flavor",
          "name": "FlavorText",
          "value": "\u003cem\u003eAll must fall, and those who stand highest fall hardest.\u003c/em\u003e"
        }
      ],
      "groupId": 1475,
      "imageCount": 1,
      "imageUrl": "https://tcgplayer-cdn.tcgplayer.com/product/92305_200w.jpg",
      "modifiedOn": "2022-03-19T07:27:52.243",
      "name": "Virtue's Ruin",
      "presaleInfo": {
        "isPresale": false,
        "note": null,
        "releasedOn": null
      },
      "productId": 92305,
      "url": "https://www.tcgplayer.com/product/92305/magic-from-the-vault-annihilation-virtues-ruin"
    }
  ],
  "success": true,
  "totalItems": 16
}