{
  "errors": [],
  "results": [
    {
      "categoryId": 3,
      "cleanName": "XY Trainer Kit Bisharp and Wigglytuff",
      "extendedData": [],
      "groupId": 1533,
      "imageCount": 1,
      "imageUrl": "https://tcgplayer-cdn.tcgplayer.com/product/97792_200w.jpg",
      "modifiedOn": "2021-07-02T21:31:47.07",
      "name": "XY Trainer Kit: Bisharp \u0026 Wigglytuff",
      "presaleInfo": {
        "isPresale": false,
        "note": null,
        "releasedOn": null
      },
      "productId": 97792,
      "url": "https://www.tcgplayer.com/product/97792/pokemon-xy-trainer-kit-bisharp-and-wigglytuff-xy-trainer-kit-bisharp-and-wigglytuff"
    },
    {
      "categoryId": 3,
      "cleanName": "Fletchling",
      "extendedData": [
        {
          "displayName": "Card Number",
          "name": "Number",
          "value": "1/30"
        },
        {
          "displayName": "Rarity",
          "name": "Rarity",
          "value": "Common"
        },
        {
          "displayName": "Card Type",
          "name": "Card Type",
          "value": "Colorless"
        },
        {
          "displayName": "HP",
          "name": "HP",
          "value": "50"
        },
        {
          "displayName": "Stage",
          "name": "Stage",
          "value": "Basic"
        },
        {
          "displayName": "Attack 1",
          "name": "Attack 1",
          "value": "[1] Me First\r\n\u003cbr\u003eDraw a card."
        },
        {
          "displayName": "Attack 2",
          "name": "Attack 2",
          "value": "[2] Peck (20)"
        },
        {
          "displayName": "Weakness",
          "name": "Weakness",
          "value": "Lx2"
        },
        {
          "displayName": "Resistance",
          "name": "Resistance",
          "value": "F-20"
        },
        {
          "displayName": "Retreat Cost",
          "name": "RetreatCost",
          "value": "1"
        }
      ],
      "groupId": 1533,
      "imageCount": 0,
      "imageUrl": "https://tcgplayer-cdn.tcgplayer.com/product/98147_200w.jpg",
      "modifiedOn": "2022-12-16T15:56:51.053",
      "name": "Fletchling",
      "presaleInfo": {
        "isPresale": false,
        "note": null,
        "releasedOn": null
      },
      "productId": 98147,
      "url": "https://www.tcgplayer.com/product/98147/pokemon-xy-trainer-kit-bisharp-and-wigglytuff-fletchling"
    },
    {
      "categoryId": 3,
      "cleanName": "Metal Energy 2",
      "extendedData": [
        {
          "displayName": "Card Number",
          "name": "Number",
          "value": "2/30"
        },
        {
          "displayName": "Rarity",
          "name": "Rarity",
          "value": "Common"
        },
        {
          "displayName": "Card Type",
          "name": "Card Type",
          "value": "Basic Energy"
        }
      ],
      "groupId": 1533,
      "imageCount": 0,
      "imageUrl": "https://tcgplayer-cdn.tcgplayer.com/product/98148_200w.jpg",
      "modifiedOn": "2022-12-16T15:57:04.213",
      "name": "Metal Energy (#2)",
      "presaleInfo": {
        "isPresale": false,
        "note": null,
        "releasedOn": null
      },
      "productId": 98148,
      "url": "https://www.tcgplayer.com/product/98148/pokemon-xy-trainer-kit-bisharp-and-wigglytuff-metal-energy-2"
    },
    {
      "categoryId": 3,
      "cleanName": "Metal Energy 3",
      "extendedData": [
        {
          "displayName": "Card Number",
          "name": "Number",
          "value": "3/30"
        },
        {
          "displayName": "Rarity",
          "name": "Rarity",
          "value": "Common"
        },
        {
          "displayName": "Card Type",
          "name": "Card Type",
          "value": "Basic Energy"
        }
      ],
      "groupId": 1533,
      "imageCount": 0,
      "imageUrl": "https://tcgplayer-cdn.tcgplayer.com/product/98149_200w.jpg",
      "modifiedOn": "2022-12-16T15:57:25.953",
      "name": "Metal Energy (#3)",
      "presaleInfo": {
        "isPresale": false,
        "note": null,
        "releasedOn": null
      },
      "productId": 98149,
      "url": "https://www.tcgplayer.com/product/98149/pokemon-xy-trainer-kit-bisharp-and-wigglytuff-metal-energy-3"
    },
    {
      "categoryId": 3,
      "cleanName": "Metal Energy 5",
      "extendedData": [
        {
          "displayName": "Card Number",
          "name": "Number",
          "value": "5/30"
        },
        {
          "displayName": "Rarity",
          "name": "Rarity",
          "value": "Common"
        },
        {
          "displayName": "Card Type",
          "name": "Card Type",
          "value": "Basic Energy"
        }
      ],
      "groupId": 1533,
      "imageCount": 0,
      "imageUrl": "https://tcgplayer-cdn.tcgplayer.com/product/98150_200w.jpg",
      "modifiedOn": "2022-12-16T15:58:34.837",
      "name": "Metal Energy (#5)",
      "presaleInfo": {
        "isPresale": false,
        "note": null,
        "releasedOn": null
      },
      "productId": 98150,
      "url": "https://www.tcgplayer.com/product/98150/pokemon-xy-trainer-kit-bisharp-and-wigglytuff-metal-energy-5"
    },
    {
      "categoryId": 3,
      "cleanName": "Metal Energy 6",
      "extendedData": [
        {
          "displayName": "Card Number",
          "name": "Number",
          "value": "6/30"
        },
        {
          "displayName": "Rarity",
          "name": "Rarity",
          "value": "Common"
        },
        {
          "displayName": "Card Type",
          "name": "Card Type",
          "value": "Basic Energy"
        }
      ],
      "groupId": 1533,
      "imageCount": 0,
      "imageUrl": "https://tcgplayer-cdn.tcgplayer.com/product/98151_200w.jpg",
      "modifiedOn": "2022-12-16T15:58:46.827",
      "name": "Metal Energy (#6)",
      "presaleInfo": {
        "isPresale": false,
        "note": null,
        "releasedOn": null
      },
      "productId": 98151,
      "url": "https://www.tcgplayer.com/product/98151/pokemon-xy-trainer-kit-bisharp-and-wigglytuff-metal-energy-6"
    },
    {
      "categoryId": 3,
      "cleanName": "Metal Energy 7",
      "extendedData": [
        {
          "displayName": "Card Number",
          "name": "Number",
          "value": "7/30"
        },
        {
          "displayName": "Rarity",
          "name": "Rarity",
          "value": "Common"
        },
        {
          "displayName": "Card Type",
          "name": "Card Type",
          "value": "Basic Energy"
        }
      ],
      "groupId": 1533,
      "imageCount": 0,
      "imageUrl": "https://tcgplayer-cdn.tcgplayer.com/product/98152_200w.jpg",
      "modifiedOn": "2022-12-16T15:58:59.057",
      "name": "Metal Energy (#7)",
      "presaleInfo": {
        "isPresale": false,
        "note": null,
        "releasedOn": null
      },
      "productId": 98152,
      "url": "https://www.tcgplayer.com/product/98152/pokemon-xy-trainer-kit-bisharp-and-wigglytuff-metal-energy-7"
    },
    {
      "categoryId": 3,
      "cleanName": "Metal Energy 8",
      "extendedData": [
        {
          "displayName": "Card Number",
          "name": "Number",
          "value": "8/30"
        },
        {
          "displayName": "Rarity",
          "name": "Rarity",
          "value": "Common"
        },
        {
          "displayName": "Card Type",
          "name": "Card Type",
          "value": "Basic Energy"
        }
      ],
      "groupId": 1533,
      "imageCount": 0,
      "imageUrl": "https://tcgplayer-cdn.tcgplayer.com/product/98153_200w.jpg",
      "modifiedOn": "2022-12-16T15:59:19.39",
      "name": "Metal Energy (#8)",
      "presaleInfo": {
        "isPresale": false,
        "note": null,
        "releasedOn": null
      },
      "productId": 98153,
      "url": "https://www.tcgplayer.com/product/98153/pokemon-xy-trainer-kit-bisharp-and-wigglytuff-metal-energy-8"
    },
    {
      "categoryId": 3,
      "cleanName": "Metal Energy 9",
      "extendedData": [
        {
          "displayName": "Card Number",
          "name": "Number",
          "value": "9/30"
        },
        {
          "displayName": "Rarity",
          "name": "Rarity",
          "value": "Common"
        },
        {
          "displayName": "Card Type",
          "name": "Card Type",
          "value": "Basic Energy"
        }
      ],
      "groupId": 1533,
      "imageCount": 0,
      "imageUrl": "https://tcgplayer-cdn.tcgplayer.com/product/98154_200w.jpg",
      "modifiedOn": "2022-12-16T15:59:29.627",
      "name": "Metal Energy (#9)",
      "presaleInfo": {
        "isPresale": false,
        "note": null,
        "releasedOn": null
      },
      "productId": 98154,
      "url": "https://www.tcgplayer.com/product/98154/pokemon-xy-trainer-kit-bisharp-and-wigglytuff-metal-energy-9"
    },
    {
      "categoryId": 3,
      "cleanName": "Metal Energy 10",
      "extendedData": [
        {
          "displayName": "Card Number",
          "name": "Number",
          "value": "10/30"
        },
        {
          "displayName": "Rarity",
          "name": "Rarity",
          "value": "Common"
        },
        {
          "displayName": "Card Type",
          "name": "Card Type",
          "value": "Basic Energy"
        }
      ],
      "groupId": 1533,
      "imageCount": 0,
      "imageUrl": "https://tcgplayer-cdn.tcgplayer.com/product/98155_200w.jpg",
      "modifiedOn": "2022-12-16T15:59:40.343",
      "name": "Metal Energy (#10)",
      "presaleInfo": {
        "isPresale": false,
        "note": null,
        "releasedOn": null
      },
      "productId": 98155,
      "url": "https://www.tcgplayer.com/product/98155/pokemon-xy-trainer-kit-bisharp-and-wigglytuff-metal-energy-10"
    },
    {
      "categoryId": 3,
      "cleanName": "Metal Energy 18",
      "extendedData": [
        {
          "displayName": "Card Number",
          "name": "Number",
          "value": "18/30"
        },
        {
          "displayName": "Rarity",
          "name": "Rarity",
          "value": "Common"
        },
        {
          "displayName": "Card Type",
          "name": "Card Type",
          "value": "Basic Energy"
        }
      ],
      "groupId": 1533,
      "imageCount": 0,
      "imageUrl": "https://tcgplayer-cdn.tcgplayer.com/product/98156_200w.jpg",
      "modifiedOn": "2022-12-16T16:11:08.347",
      "name": "Metal Energy (#18)",
      "presaleInfo": {
        "isPresale": false,
        "note": null,
        "releasedOn": null
      },
      "productId": 98156,
      "url": "https://www.tcgplayer.com/product/98156/pokemon-xy-trainer-kit-bisharp-and-wigglytuff-metal-energy-18"
    },
    {
      "categoryId": 3,
      "cleanName": "Metal Energy 22",
      "extendedData": [
        {
          "displayName": "Card Number",
          "name": "Number",
          "value": "22/30"
        },
        {
          "displayName": "Rarity",
          "name": "Rarity",
          "value": "Common"
        },
        {
          "displayName": "Card Type",
          "name": "Card Type",
          "value": "Basic Energy"
        }
      ],
      "groupId": 1533,
      "imageCount": 0,
      "imageUrl": "https://tcgplayer-cdn.tcgplayer.com/product/98157_200w.jpg",
      "modifiedOn": "2022-12-16T16:13:02.827",
      "name": "Metal Energy (#22)",
      "presaleInfo": {
        "isPresale": false,
        "note": null,
        "releasedOn": null
      },
      "productId": 98157,
      "url": "https://www.tcgplayer.com/product/98157/pokemon-xy-trainer-kit-bisharp-and-wigglytuff-metal-energy-22"
    },
    {
      "categoryId": 3,
      "cleanName": "Metal Energy 24",
      "extendedData": [
        {
          "displayName": "Card Number",
          "name": "Number",
          "value": "24/30"
        },
        {
          "displayName": "Rarity",
          "name": "Rarity",
          "value": "Common"
        },
        {
          "displayName": "Card Type",
          "name": "Card Type",
          "value": "Basic Energy"
        }
      ],
      "groupId": 1533,
      "imageCount": 0,
      "imageUrl": "https://tcgplayer-cdn.tcgplayer.com/product/98158_200w.jpg",
      "modifiedOn": "2022-12-16T16:13:26.41",
      "name": "Metal Energy (#24)",
      "presaleInfo": {
        "isPresale": false,
        "note": null,
        "releasedOn": null
      },
      "productId": 98158,
      "url": "https://www.tcgplayer.com/product/98158/pokemon-xy-trainer-kit-bisharp-and-wigglytuff-metal-energy-24"
    },
    {
      "categoryId": 3,
      "cleanName": "Vigoroth 4",
      "extendedData": [
        {
          "displayName": "Card Number",
          "name": "Number",
          "value": "4/30"
        },
        {
          "displayName": "Rarity",
          "name": "Rarity",
          "value": "Common"
        },
        {
          "displayName": "Card Type",
          "name": "Card Type",
          "value": "Colorless"
        },
        {
          "displayName": "HP",
          "name": "HP",
          "value": "90"
        },
        {
          "displayName": "Stage",
          "name": "Stage",
          "value": "Stage 1"
        },
        {
          "displayName": "Attack 1",
          "name": "Attack 1",
          "value": "[1] Scratch (20)"
        },
        {
          "displayName": "Attack 2",
          "name": "Attack 2",
          "value": "[2] Reckless Charge (70)\r\n\u003cbr\u003eFlip a coin. If tails, this Pokemon does 20 damage to itself."
        },
        {
          "displayName": "Weakness",
          "name": "Weakness",
          "value": "Fx2"
        },
        {
          "displayName": "Resistance",
          "name": "Resistance",
          "value": "None"
        },
        {
          "displayName": "Retreat Cost",
          "name": "RetreatCost",
          "value": "0"
        }
      ],
      "groupId": 1533,
      "imageCount": 0,
      "imageUrl": "https://tcgplayer-cdn.tcgplayer.com/product/98159_200w.jpg",
      "modifiedOn": "2022-12-16T15:58:00.947",
      "name": "Vigoroth (#4)",
      "presaleInfo": {
        "isPresale": false,
        "note": null,
        "releasedOn": null
      },
      "productId": 98159,
      "url": "https://www.tcgplayer.com/product/98159/pokemon-xy-trainer-kit-bisharp-and-wigglytuff-vigoroth-4"
    },
    {
      "categoryId": 3,
      "cleanName": "Honedge 11",
      "extendedData": [
        {
          "displayName": "Card Number",
          "name": "Number",
          "value": "11/30"
        },
        {
          "displayName": "Rarity",
          "name": "Rarity",
          "value": "Common"
        },
        {
          "displayName": "Card Type",
          "name": "Card Type",
          "value": "Metal"
        },
        {
          "displayName": "HP",
          "name": "HP",
          "value": "60"
        },
        {
          "displayName": "Stage",
          "name": "Stage",
          "value": "Basic"
        },
        {
          "displayName": "Attack 1",
          "name": "Attack 1",
          "value": "[M] Pierce (10)"
        },
        {
          "displayName": "Weakness",
          "name": "Weakness",
          "value": "Rx2"
        },
        {
          "displayName": "Resistance",
          "name": "Resistance",
          "value": "P-20"
        },
        {
          "displayName": "Retreat Cost",
          "name": "RetreatCost",
          "value": "2"
        }
      ],
      "groupId": 1533,
      "imageCount": 0,
      "imageUrl": "https://tcgplayer-cdn.tcgplayer.com/product/98160_200w.jpg",
      "modifiedOn": "2022-12-16T16:00:30.36",
      "name": "Honedge (#11)",
      "presaleInfo": {
        "isPresale": false,
        "note": null,
        "releasedOn": null
      },
      "productId": 98160,
      "url": "https://www.tcgplayer.com/product/98160/pokemon-xy-trainer-kit-bisharp-and-wigglytuff-honedge-11"
    },
    {
      "categoryId": 3,
      "cleanName": "Bidoof",
      "extendedData": [
        {
          "displayName": "Card Number",
          "name": "Number",
          "value": "12/30"
        },
        {
          "displayName": "Rarity",
          "name": "Rarity",
          "value": "Common"
        },
        {
          "displayName": "Card Type",
          "name": "Card Type",
          "value": "Colorless"
        },
        {
          "displayName": "HP",
          "name": "HP",
          "value": "60"
        },
        {
          "displayName": "Stage",
          "name": "Stage",
          "value": "Basic"
        },
        {
          "displayName": "Attack 1",
          "name": "Attack 1",
          "value": "[2] Hyper Fang (40)\r\n\u003cbr\u003eFlip a coin. If tails, this attack does nothing."
        },
        {
          "displayName": "Weakness",
          "name": "Weakness",
          "value": "Fx2"
        },
        {
          "displayName": "Resistance",
          "name": "Resistance",
          "value": "None"
        },
        {
          "displayName": "Retreat Cost",
          "name": "RetreatCost",
          "value": "3"
        }
      ],
      "groupId": 1533,
      "imageCount": 0,
      "imageUrl": "https://tcgplayer-cdn.tcgplayer.com/product/98161_200w.jpg",
      "modifiedOn": "2022-12-16T16:01:01.1",
      "name": "Bidoof",
      "presaleInfo": {
        "isPresale": false,
        "note": null,
        "releasedOn": null
      },
      "productId": 98161,
      "url": "https://www.tcgplayer.com/product/98161/pokemon-xy-trainer-kit-bisharp-and-wigglytuff-bidoof"
    },
    {
      "categoryId": 3,
      "cleanName": "Pawniard 13",
      "extendedData": [
        {
          "displayName": "Card Number",
          "name": "Number",
          "value": "13/30"
        },
        {
          "displayName": "Rarity",
          "name": "Rarity",
          "value": "Common"
        },
        {
          "displayName": "Card Type",
          "name": "Card Type",
          "value": "Metal"
        },
        {
          "displayName": "HP",
          "name": "HP",
          "value": "60"
        },
        {
          "displayName": "Stage",
          "name": "Stage",
          "value": "Basic"
        },
        {
          "displayName": "Attack 1",
          "name": "Attack 1",
          "value": "[M] Pierce (10)"
        },
        {
          "displayName": "Attack 2",
          "name": "Attack 2",
          "value": "[2] Cut (20)"
        },
        {
          "displayName": "Weakness",
          "name": "Weakness",
          "value": "Rx2"
        },
        {
          "displayName": "Resistance",
          "name": "Resistance",
          "value": "P-20"
        },
        {
          "displayName": "Retreat Cost",
          "name": "RetreatCost",
          "value": "1"
        }
      ],
      "groupId": 1533,
      "imageCount": 0,
      "imageUrl": "https://tcgplayer-cdn.tcgplayer.com/product/98162_200w.jpg",
      "modifiedOn": "2022-12-16T16:01:28.387",
      "name": "Pawniard (#13)",
      "presaleInfo": {
        "isPresale": false,
        "note": null,
        "releasedOn": null
      },
      "productId": 98162,
      "url": "https://www.tcgplayer.com/product/98162/pokemon-xy-trainer-kit-bisharp-and-wigglytuff-pawniard-13"
    },
    {
      "categoryId": 3,
      "cleanName": "Doublade 14",
      "extendedData": [
        {
          "displayName": "Card Number",
          "name": "Number",
          "value": "14/30"
        },
        {
          "displayName": "Rarity",
          "name": "Rarity",
          "value": "Common"
        },
        {
          "displayName": "Card Type",
          "name": "Card Type",
          "value": "Metal"
        },
        {
          "displayName": "HP",
          "name": "HP",
          "value": "80"
        },
        {
          "displayName": "Stage",
          "name": "Stage",
          "value": "Stage 1"
        },
        {
          "displayName": "Attack 1",
          "name": "Attack 1",
          "value": "[1M] Dual Blades (30x)\r\n\u003cbr\u003eFlip 2 coins. This attack does 30 damage times the number of heads."
        },
        {
          "displayName": "Weakness",
          "name": "Weakness",
          "value": "Rx2"
        },
        {
          "displayName": "Resistance",
          "name": "Resistance",
          "value": "P-20"
        },
        {
          "displayName": "Retreat Cost",
          "name": "RetreatCost",
          "value": "2"
        }
      ],
      "groupId": 1533,
      "imageCount": 0,
      "imageUrl": "https://tcgplayer-cdn.tcgplayer.com/product/98163_200w.jpg",
      "modifiedOn": "2022-12-16T16:09:59.62",
      "name": "Doublade (#14)",
      "presaleInfo": {
        "isPresale": false,
        "note": null,
        "releasedOn": null
      },
      "productId": 98163,
      "url": "https://www.tcgplayer.com/product/98163/pokemon-xy-trainer-kit-bisharp-and-wigglytuff-doublade-14"
    },
    {
      "categoryId": 3,
      "cleanName": "Slakoth 15",
      "extendedData": [
        {
          "displayName": "Card Number",
          "name": "Number",
          "value": "15/30"
        },
        {
          "displayName": "Rarity",
          "name": "Rarity",
          "value": "Common"
        },
        {
          "displayName": "Card Type",
          "name": "Card Type",
          "value": "Colorless"
        },
        {
          "displayName": "HP",
          "name": "HP",
          "value": "60"
        },
        {
          "displayName": "Stage",
          "name": "Stage",
          "value": "Basic"
        },
        {
          "displayName": "Attack 1",
          "name": "Attack 1",
          "value": "[2] Big Yawn\r\n\u003cbr\u003eBoth Active Pokemon are now Asleep."
        },
        {
          "displayName": "Weakness",
          "name": "Weakness",
          "value": "Fx2"
        },
        {
          "displayName": "Resistance",
          "name": "Resistance",
          "value": "None"
        },
        {
          "displayName": "Retreat Cost",
          "name": "RetreatCost",
          "value": "3"
        }
      ],
      "groupId": 1533,
      "imageCount": 0,
      "imageUrl": "https://tcgplayer-cdn.tcgplayer.com/product/98164_200w.jpg",
      "modifiedOn": "2022-12-16T16:10:29.42",
      "name": "Slakoth (#15)",
      "presaleInfo": {
        "isPresale": false,
        "note": null,
        "releasedOn": null
      },
      "productId": 98164,
      "url": "https://www.tcgplayer.com/product/98164/pokemon-xy-trainer-kit-bisharp-and-wigglytuff-slakoth-15"
    },
    {
      "categoryId": 3,
      "cleanName": "Bisharp 16 Non Holo",
      "extendedData": [
        {
          "displayName": "Card Number",
          "name": "Number",
          "value": "16/30"
        },
        {
          "displayName": "Rarity",
          "name": "Rarity",
          "value": "Common"
        },
        {
          "displayName": "Card Type",
          "name": "Card Type",
          "value": "Metal"
        },
        {
          "displayName": "HP",
          "name": "HP",
          "value": "90"
        },
        {
          "displayName": "Stage",
          "name": "Stage",
          "value": "Stage 1"
        },
        {
          "displayName": "Attack 1",
          "name": "Attack 1",
          "value": "[M] Wicked Jab (20)\r\n\u003cbr\u003eFlip a coin. If heads, your opponent's Active Pokemon is now Paralyzed."
        },
        {
          "displayName": "Attack 2",
          "name": "Attack 2",
          "value": "[2M] Metal Claw (70)"
        },
        {
          "displayName": "Weakness",
          "name": "Weakness",
          "value": "Rx2"
        },
        {
          "displayName": "Resistance",
          "name": "Resistance",
          "value": "P-20"
        },
        {
          "displayName": "Retreat Cost",
          "name": "RetreatCost",
          "value": "1"
        }
      ],
      "groupId": 1533,
      "imageCount": 0,
      "imageUrl": "https://tcgplayer-cdn.tcgplayer.com/product/98165_200w.jpg",
      "modifiedOn": "2022-12-16T16:10:36.56",
      "name": "Bisharp (#16 Non-Holo)",
      "presaleInfo": {
        "isPresale": false,
        "note": null,
        "releasedOn": null
      },
      "productId": 98165,
      "url": "https://www.tcgplayer.com/product/98165/pokemon-xy-trainer-kit-bisharp-and-wigglytuff-bisharp-16-non-holo"
    },
    {
      "categoryId": 3,
      "cleanName": "Patrat",
      "extendedData": [
        {
          "displayName": "Card Number",
          "name": "Number",
          "value": "17/30"
        },
        {
          "displayName": "Rarity",
          "name": "Rarity",
          "value": "Common"
        },
        {
          "displayName": "Card Type",
          "name": "Card Type",
          "value": "Colorless"
        },
        {
          "displayName": "HP",
          "name": "HP",
          "value": "60"
        },
        {
          "displayName": "Stage",
          "name": "Stage",
          "value": "Basic"
        },
        {
          "displayName": "Attack 1",
          "name": "Attack 1",
          "value": "[1] Safety Check\r\n\u003cbr\u003eLook at 1 of your face-down Prize cards."
        },
        {
          "displayName": "Weakness",
          "name": "Weakness",
          "value": "Fx2"
        },
        {
          "displayName": "Resistance",
          "name": "Resistance",
          "value": "None"
        },
        {
          "displayName": "Retreat Cost",
          "name": "RetreatCost",
          "value": "1"
        }
      ],
      "groupId": 1533,
      "imageCount": 0,
      "imageUrl": "https://tcgplayer-cdn.tcgplayer.com/product/98166_200w.jpg",
      "modifiedOn": "2022-12-16T16:10:58.56",
      "name": "Patrat",
      "presaleInfo": {
        "isPresale": false,
        "note": null,
        "releasedOn": null
      },
      "productId": 98166,
      "url": "https://www.tcgplayer.com/product/98166/pokemon-xy-trainer-kit-bisharp-and-wigglytuff-patrat"
    },
    {
      "categoryId": 3,
      "cleanName": "Tierno Bisharp",
      "extendedData": [
        {
          "displayName": "Card Number",
          "name": "Number",
          "value": "19/30"
        },
        {
          "displayName": "Rarity",
          "name": "Rarity",
          "value": "Common"
        },
        {
          "displayName": "Card Type",
          "name": "Card Type",
          "value": "Supporter"
        },
        {
          "displayName": "Card Text",
          "name": "CardText",
          "value": "Draw 3 cards."
        }
      ],
      "groupId": 1533,
      "imageCount": 0,
      "imageUrl": "https://tcgplayer-cdn.tcgplayer.com/product/98167_200w.jpg",
      "modifiedOn": "2022-12-16T16:11:34.333",
      "name": "Tierno (Bisharp)",
      "presaleInfo": {
        "isPresale": false,
        "note": null,
        "releasedOn": null
      },
      "productId": 98167,
      "url": "https://www.tcgplayer.com/product/98167/pokemon-xy-trainer-kit-bisharp-and-wigglytuff-tierno-bisharp"
    },
    {
      "categoryId": 3,
      "cleanName": "Trevor Bisharp",
      "extendedData": [
        {
          "displayName": "Card Number",
          "name": "Number",
          "value": "20/30"
        },
        {
          "displayName": "Rarity",
          "name": "Rarity",
          "value": "Common"
        },
        {
          "displayName": "Card Type",
          "name": "Card Type",
          "value": "Supporter"
        },
        {
          "displayName": "Card Text",
          "name": "CardText",
          "value": "Search your deck for a Pokemon, reveal it, and put it into your hand. Shuffle your deck afterward."
        }
      ],
      "groupId": 1533,
      "imageCount": 1,
      "imageUrl": "https://tcgplayer-cdn.tcgplayer.com/product/98168_200w.jpg",
      "modifiedOn": "2022-12-16T16:11:48.53",
      "name": "Trevor (Bisharp)",
      "presaleInfo": {
        "isPresale": false,
        "note": null,
        "releasedOn": null
      },
      "productId": 98168,
      "url": "https://www.tcgplayer.com/product/98168/pokemon-xy-trainer-kit-bisharp-and-wigglytuff-trevor-bisharp"
    },
    {
      "categoryId": 3,
      "cleanName": "Pawniard 21",
      "extendedData": [
        {
          "displayName": "Card Number",
          "name": "Number",
          "value": "21/30"
        },
        {
          "displayName": "Rarity",
          "name": "Rarity",
          "value": "Common"
        },
        {
          "displayName": "Card Type",
          "name": "Card Type",
          "value": "Metal"
        },
        {
          "displayName": "HP",
          "name": "HP",
          "value": "60"
        },
        {
          "displayName": "Stage",
          "name": "Stage",
          "value": "Basic"
        },
        {
          "displayName": "Attack 1",
          "name": "Attack 1",
          "value": "[M] Pierce (10)"
        },
        {
          "displayName": "Attack 2",
          "name": "Attack 2",
          "value": "[2] Cut (20)"
        },
        {
          "displayName": "Weakness",
          "name": "Weakness",
          "value": "Rx2"
        },
        {
          "displayName": "Resistance",
          "name": "Resistance",
          "value": "P-20"
        },
        {
          "displayName": "Retreat Cost",
          "name": "RetreatCost",
          "value": "1"
        }
      ],
      "groupId": 1533,
      "imageCount": 0,
      "imageUrl": "https://tcgplayer-cdn.tcgplayer.com/product/98169_200w.jpg",
      "modifiedOn": "2022-12-16T16:12:47.76",
      "name": "Pawniard (#21)",
      "presaleInfo": {
        "isPresale": false,
        "note": null,
        "releasedOn": null
      },
      "productId": 98169,
      "url": "https://www.tcgplayer.com/product/98169/pokemon-xy-trainer-kit-bisharp-and-wigglytuff-pawniard-21"
    },
    {
      "categoryId": 3,
      "cleanName": "Doublade 23",
      "extendedData": [
        {
          "displayName": "Card Number",
          "name": "Number",
          "value": "23/30"
        },
        {
          "displayName": "Rarity",
          "name": "Rarity",
          "value": "Common"
        },
        {
          "displayName": "Card Type",
          "name": "Card Type",
          "value": "Metal"
        },
        {
          "displayName": "HP",
          "name": "HP",
          "value": "80"
        },
        {
          "displayName": "Stage",
          "name": "Stage",
          "value": "Stage 1"
        },
        {
          "displayName": "Attack 1",
          "name": "Attack 1",
          "value": "[1M] Dual Blades (30x)\r\n\u003cbr\u003eFlip 2 coins. This attack does 30 damage times the number of heads."
        },
        {
          "displayName": "Weakness",
          "name": "Weakness",
          "value": "Rx2"
        },
        {
          "displayName": "Resistance",
          "name": "Resistance",
          "value": "P-20"
        },
        {
          "displayName": "Retreat Cost",
          "name": "RetreatCost",
          "value": "2"
        }
      ],
      "groupId": 1533,
      "imageCount": 0,
      "imageUrl": "https://tcgplayer-cdn.tcgplayer.com/product/98170_200w.jpg",
      "modifiedOn": "2022-12-16T16:13:10.383",
      "name": "Doublade (#23)",
      "presaleInfo": {
        "isPresale": false,
        "note": null,
        "releasedOn": null
      },
      "productId": 98170,
      "url": "https://www.tcgplayer.com/product/98170/pokemon-xy-trainer-kit-bisharp-and-wigglytuff-doublade-23"
    },
    {
      "categoryId": 3,
      "cleanName": "Potion 25 Bisharp",
      "extendedData": [
        {
          "displayName": "Card Number",
          "name": "Number",
          "value": "25/30"
        },
        {
          "displayName": "Rarity",
          "name": "Rarity",
          "value": "Common"
        },
        {
          "displayName": "Card Type",
          "name": "Card Type",
          "value": "Item"
        },
        {
          "displayName": "Card Text",
          "name": "CardText",
          "value": "Heal 30 damage from 1 of your Pokemon."
        }
      ],
      "groupId": 1533,
      "imageCount": 0,
      "imageUrl": "https://tcgplayer-cdn.tcgplayer.com/product/98171_200w.jpg",
      "modifiedOn": "2022-12-16T16:13:48.367",
      "name": "Potion (#25 - Bisharp)",
      "presaleInfo": {
        "isPresale": false,
        "note": null,
        "releasedOn": null
      },
      "productId": 98171,
      "url": "https://www.tcgplayer.com/product/98171/pokemon-xy-trainer-kit-bisharp-and-wigglytuff-potion-25-bisharp"
    },
    {
      "categoryId": 3,
      "cleanName": "Potion 29 Bisharp",
      "extendedData": [
        {
          "displayName": "Card Number",
          "name": "Number",
          "value": "29/30"
        },
        {
          "displayName": "Rarity",
          "name": "Rarity",
          "value": "Common"
        },
        {
          "displayName": "Card Type",
          "name": "Card Type",
          "value": "Item"
        },
        {
          "displayName": "Card Text",
          "name": "CardText",
          "value": "Heal 30 damage from 1 of your Pokemon."
        }
      ],
      "groupId": 1533,
      "imageCount": 0,
      "imageUrl": "https://tcgplayer-cdn.tcgplayer.com/product/98172_200w.jpg",
      "modifiedOn": "2022-12-16T16:14:49.95",
      "name": "Potion (#29 - Bisharp)",
      "presaleInfo": {
        "isPresale": false,
        "note": null,
        "releasedOn": null
      },
      "productId": 98172,
      "url": "https://www.tcgplayer.com/product/98172/pokemon-xy-trainer-kit-bisharp-and-wigglytuff-potion-29-bisharp"
    },
    {
      "categoryId": 3,
      "cleanName": "Slakoth 26",
      "extendedData": [
        {
          "displayName": "Card Number",
          "name": "Number",
          "value": "26/30"
        },
        {
          "displayName": "Rarity",
          "name": "Rarity",
          "value": "Common"
        },
        {
          "displayName": "Card Type",
          "name": "Card Type",
          "value": "Colorless"
        },
        {
          "displayName": "HP",
          "name": "HP",
          "value": "60"
        },
        {
          "displayName": "Stage",
          "name": "Stage",
          "value": "Basic"
        },
        {
          "displayName": "Attack 1",
          "name": "Attack 1",
          "value": "[2] Big Yawn\r\n\u003cbr\u003eBoth Active Pokemon are now Asleep."
        },
        {
          "displayName": "Weakness",
          "name": "Weakness",
          "value": "Fx2"
        },
        {
          "displayName": "Resistance",
          "name": "Resistance",
          "value": "None"
        },
        {
          "displayName": "Retreat Cost",
          "name": "RetreatCost",
          "value": "3"
        }
      ],
      "groupId": 1533,
      "imageCount": 0,
      "imageUrl": "https://tcgplayer-cdn.tcgplayer.com/product/98173_200w.jpg",
      "modifiedOn": "2022-12-16T16:13:55.763",
      "name": "Slakoth (#26)",
      "presaleInfo": {
        "isPresale": false,
        "note": null,
        "releasedOn": null
      },
      "productId": 98173,
      "url": "https://www.tcgplayer.com/product/98173/pokemon-xy-trainer-kit-bisharp-and-wigglytuff-slakoth-26"
    },
    {
      "categoryId": 3,
      "cleanName": "Honedge 27",
      "extendedData": [
        {
          "displayName": "Card Number",
          "name": "Number",
          "value": "27/30"
        },
        {
          "displayName": "Rarity",
          "name": "Rarity",
          "value": "Common"
        },
        {
          "displayName": "Card Type",
          "name": "Card Type",
          "value": "Metal"
        },
        {
          "displayName": "HP",
          "name": "HP",
          "value": "60"
        },
        {
          "displayName": "Stage",
          "name": "Stage",
          "value": "Basic"
        },
        {
          "displayName": "Attack 1",
          "name": "Attack 1",
          "value": "[M] Pierce (10)"
        },
        {
          "displayName": "Weakness",
          "name": "Weakness",
          "value": "Rx2"
        },
        {
          "displayName": "Resistance",
          "name": "Resistance",
          "value": "P-20"
        },
        {
          "displayName": "Retreat Cost",
          "name": "RetreatCost",
          "value": "2"
        }
      ],
      "groupId": 1533,
      "imageCount": 0,
      "imageUrl": "https://tcgplayer-cdn.tcgplayer.com/product/98174_200w.jpg",
      "modifiedOn": "2022-12-16T16:14:19.323",
      "name": "Honedge (#27)",
      "presaleInfo": {
        "isPresale": false,
        "note": null,
        "releasedOn": null
      },
      "productId": 98174,
      "url": "https://www.tcgplayer.com/product/98174/pokemon-xy-trainer-kit-bisharp-and-wigglytuff-honedge-27"
    },
    {
      "categoryId": 3,
      "cleanName": "Vigoroth 28",
      "extendedData": [
        {
          "displayName": "Card Number",
          "name": "Number",
          "value": "28/30"
        },
        {
          "displayName": "Rarity",
          "name": "Rarity",
          "value": "Common"
        },
        {
          "displayName": "Card Type",
          "name": "Card Type",
          "value": "Colorless"
        },
        {
          "displayName": "HP",
          "name": "HP",
          "value": "90"
        },
        {
          "displayName": "Stage",
          "name": "Stage",
          "value": "Stage 1"
        },
        {
          "displayName": "Attack 1",
          "name": "Attack 1",
          "value": "[1] Scratch (20)"
        },
        {
          "displayName": "Attack 2",
          "name": "Attack 2",
          "value": "[2] Reckless Charge (70)\r\n\u003cbr\u003eFlip a coin. If tails, this Pokemon does 20 damage to itself."
        },
        {
          "displayName": "Weakness",
          "name": "Weakness",
          "value": "Fx2"
        },
        {
          "displayName": "Resistance",
          "name": "Resistance",
          "value": "None"
        },
        {
          "displayName": "Retreat Cost",
          "name": "RetreatCost",
          "value": "0"
        }
      ],
      "groupId": 1533,
      "imageCount": 0,
      "imageUrl": "https://tcgplayer-cdn.tcgplayer.com/product/98175_200w.jpg",
      "modifiedOn": "2022-12-16T16:14:35.597",
      "name": "Vigoroth (#28)",
      "presaleInfo": {
        "isPresale": false,
        "note": null,
        "releasedOn": null
      },
      "productId": 98175,
      "url": "https://www.tcgplayer.com/product/98175/pokemon-xy-trainer-kit-bisharp-and-wigglytuff-vigoroth-28"
    },
    {
      "categoryId": 3,
      "cleanName": "Bisharp 30 Holo",
      "extendedData": [
        {
          "displayName": "Card Number",
          "name": "Number",
          "value": "30/30"
        },
        {
          "displayName": "Rarity",
          "name": "Rarity",
          "value": "Common"
        },
        {
          "displayName": "Card Type",
          "name": "Card Type",
          "value": "Metal"
        },
        {
          "displayName": "HP",
          "name": "HP",
          "value": "90"
        },
        {
          "displayName": "Stage",
          "name": "Stage",
          "value": "Stage 1"
        },
        {
          "displayName": "Attack 1",
          "name": "Attack 1",
          "value": "[M] Wicked Jab (20)\r\n\u003cbr\u003eFlip a coin. If heads, your opponent's Active Pokemon is now Paralyzed."
        },
        {
          "displayName": "Attack 2",
          "name": "Attack 2",
          "value": "[2M] Metal Claw (70)"
        },
        {
          "displayName": "Weakness",
          "name": "Weakness",
          "value": "Rx2"
        },
        {
          "displayName": "Resistance",
          "name": "Resistance",
          "value": "P-20"
        },
        {
          "displayName": "Retreat Cost",
          "name": "RetreatCost",
          "value": "1"
        }
      ],
      "groupId": 1533,
      "imageCount": 0,
      "imageUrl": "https://tcgplayer-cdn.tcgplayer.com/product/98176_200w.jpg",
      "modifiedOn": "2022-12-16T16:14:57.13",
      "name": "Bisharp (#30 Holo)",
      "presaleInfo": {
        "isPresale": false,
        "note": null,
        "releasedOn": null
      },
      "productId": 98176,
      "url": "https://www.tcgplayer.com/product/98176/pokemon-xy-trainer-kit-bisharp-and-wigglytuff-bisharp-30-holo"
    },
    {
      "categoryId": 3,
      "cleanName": "Swirlix 1",
      "extendedData": [
        {
          "displayName": "Card Number",
          "name": "Number",
          "value": "1/30"
        },
        {
          "displayName": "Rarity",
          "name": "Rarity",
          "value": "Common"
        },
        {
          "displayName": "Card Type",
          "name": "Card Type",
          "value": "Fairy"
        },
        {
          "displayName": "HP",
          "name": "HP",
          "value": "60"
        },
        {
          "displayName": "Stage",
          "name": "Stage",
          "value": "Basic"
        },
        {
          "displayName": "Attack 1",
          "name": "Attack 1",
          "value": "[Y] Draining Kiss (10)\r\n\u003cbr\u003eHeal 10 damage from this Pokemon."
        },
        {
          "displayName": "Weakness",
          "name": "Weakness",
          "value": "Mx2"
        },
        {
          "displayName": "Resistance",
          "name": "Resistance",
          "value": "D-20"
        },
        {
          "displayName": "Retreat Cost",
          "name": "RetreatCost",
          "value": "1"
        }
      ],
      "groupId": 1533,
      "imageCount": 0,
      "imageUrl": "https://tcgplayer-cdn.tcgplayer.com/product/98177_200w.jpg",
      "modifiedOn": "2022-12-16T15:56:56.873",
      "name": "Swirlix (#1)",
      "presaleInfo": {
        "isPresale": false,
        "note": null,
        "releasedOn": null
      },
      "productId": 98177,
      "url": "https://www.tcgplayer.com/product/98177/pokemon-xy-trainer-kit-bisharp-and-wigglytuff-swirlix-1"
    },
    {
      "categoryId": 3,
      "cleanName": "Pidgeotto 2",
      "extendedData": [
        {
          "displayName": "Card Number",
          "name": "Number",
          "value": "2/30"
        },
        {
          "displayName": "Rarity",
          "name": "Rarity",
          "value": "Common"
        },
        {
          "displayName": "Card Type",
          "name": "Card Type",
          "value": "Colorless"
        },
        {
          "displayName": "HP",
          "name": "HP",
          "value": "80"
        },
        {
          "displayName": "Stage",
          "name": "Stage",
          "value": "Stage 1"
        },
        {
          "displayName": "Attack 1",
          "name": "Attack 1",
          "value": "[1] Sand Attack \r\n\u003cbr\u003eIf the Defending Pokemon tries to attack during your opponent's next turn, your opponent flips a coin. If tails, that attack does nothing."
        },
        {
          "displayName": "Attack 2",
          "name": "Attack 2",
          "value": "[2] Ambush (20+)\r\n\u003cbr\u003eFlip a coin. If heads, this attack does 20 more damage."
        },
        {
          "displayName": "Weakness",
          "name": "Weakness",
          "value": "Lx2"
        },
        {
          "displayName": "Resistance",
          "name": "Resistance",
          "value": "F-20"
        },
        {
          "displayName": "Retreat Cost",
          "name": "RetreatCost",
          "value": "1"
        }
      ],
      "groupId": 1533,
      "imageCount": 0,
      "imageUrl": "https://tcgplayer-cdn.tcgplayer.com/product/98178_200w.jpg",
      "modifiedOn": "2022-12-16T15:57:10.423",
      "name": "Pidgeotto (#2)",
      "presaleInfo": {
        "isPresale": false,
        "note": null,
        "releasedOn": null
      },
      "productId": 98178,
      "url": "https://www.tcgplayer.com/product/98178/pokemon-xy-trainer-kit-bisharp-and-wigglytuff-pidgeotto-2"
    },
    {
      "categoryId": 3,
      "cleanName": "Fairy Energy 3",
      "extendedData": [
        {
          "displayName": "Card Number",
          "name": "Number",
          "value": "3/30"
        },
        {
          "displayName": "Rarity",
          "name": "Rarity",
          "value": "Common"
        },
        {
          "displayName": "Card Type",
          "name": "Card Type",
          "value": "Basic Energy"
        }
      ],
      "groupId": 1533,
      "imageCount": 0,
      "imageUrl": "https://tcgplayer-cdn.tcgplayer.com/product/98179_200w.jpg",
      "modifiedOn": "2022-12-16T15:57:19.117",
      "name": "Fairy Energy (#3)",
      "presaleInfo": {
        "isPresale": false,
        "note": null,
        "releasedOn": null
      },
      "productId": 98179,
      "url": "https://www.tcgplayer.com/product/98179/pokemon-xy-trainer-kit-bisharp-and-wigglytuff-fairy-energy-3"
    },
    {
      "categoryId": 3,
      "cleanName": "Fairy Energy 5",
      "extendedData": [
        {
          "displayName": "Card Number",
          "name": "Number",
          "value": "5/30"
        },
        {
          "displayName": "Rarity",
          "name": "Rarity",
          "value": "Common"
        },
        {
          "displayName": "Card Type",
          "name": "Card Type",
          "value": "Basic Energy"
        }
      ],
      "groupId": 1533,
      "imageCount": 0,
      "imageUrl": "https://tcgplayer-cdn.tcgplayer.com/product/98180_200w.jpg",
      "modifiedOn": "2022-12-16T15:58:26.417",
      "name": "Fairy Energy (#5)",
      "presaleInfo": {
        "isPresale": false,
        "note": null,
        "releasedOn": null
      },
      "productId": 98180,
      "url": "https://www.tcgplayer.com/product/98180/pokemon-xy-trainer-kit-bisharp-and-wigglytuff-fairy-energy-5"
    },
    {
      "categoryId": 3,
      "cleanName": "Fairy Energy 6",
      "extendedData": [
        {
          "displayName": "Card Number",
          "name": "Number",
          "value": "6/30"
        },
        {
          "displayName": "Rarity",
          "name": "Rarity",
          "value": "Common"
        },
        {
          "displayName": "Card Type",
          "name": "Card Type",
          "value": "Basic Energy"
        }
      ],
      "groupId": 1533,
      "imageCount": 0,
      "imageUrl": "https://tcgplayer-cdn.tcgplayer.com/product/98181_200w.jpg",
      "modifiedOn": "2022-12-16T15:58:41.333",
      "name": "Fairy Energy (#6)",
      "presaleInfo": {
        "isPresale": false,
        "note": null,
        "releasedOn": null
      },
      "productId": 98181,
      "url": "https://www.tcgplayer.com/product/98181/pokemon-xy-trainer-kit-bisharp-and-wigglytuff-fairy-energy-6"
    },
    {
      "categoryId": 3,
      "cleanName": "Fairy Energy 7",
      "extendedData": [
        {
          "displayName": "Card Number",
          "name": "Number",
          "value": "7/30"
        },
        {
          "displayName": "Rarity",
          "name": "Rarity",
          "value": "Common"
        },
        {
          "displayName": "Card Type",
          "name": "Card Type",
          "value": "Basic Energy"
        }
      ],
      "groupId": 1533,
      "imageCount": 0,
      "imageUrl": "https://tcgplayer-cdn.tcgplayer.com/product/98182_200w.jpg",
      "modifiedOn": "2022-12-16T15:58:53.013",
      "name": "Fairy Energy (#7)",
      "presaleInfo": {
        "isPresale": false,
        "note": null,
        "releasedOn": null
      },
      "productId": 98182,
      "url": "https://www.tcgplayer.com/product/98182/pokemon-xy-trainer-kit-bisharp-and-wigglytuff-fairy-energy-7"
    },
    {
      "categoryId": 3,
      "cleanName": "Fairy Energy 8",
      "extendedData": [
        {
          "displayName": "Card Number",
          "name": "Number",
          "value": "8/30"
        },
        {
          "displayName": "Rarity",
          "name": "Rarity",
          "value": "Common"
        },
        {
          "displayName": "Card Type",
          "name": "Card Type",
          "value": "Basic Energy"
        }
      ],
      "groupId": 1533,
      "imageCount": 0,
      "imageUrl": "https://tcgplayer-cdn.tcgplayer.com/product/98183_200w.jpg",
      "modifiedOn": "2022-12-16T15:59:13.707",
      "name": "Fairy Energy (#8)",
      "presaleInfo": {
        "isPresale": false,
        "note": null,
        "releasedOn": null
      },
      "productId": 98183,
      "url": "https://www.tcgplayer.com/product/98183/pokemon-xy-trainer-kit-bisharp-and-wigglytuff-fairy-energy-8"
    },
    {
      "categoryId": 3,
      "cleanName": "Fairy Energy 9",
      "extendedData": [
        {
          "displayName": "Card Number",
          "name": "Number",
          "value": "9/30"
        },
        {
          "displayName": "Rarity",
          "name": "Rarity",
          "value": "Common"
        },
        {
          "displayName": "Card Type",
          "name": "Card Type",
          "value": "Basic Energy"
        }
      ],
      "groupId": 1533,
      "imageCount": 0,
      "imageUrl": "https://tcgplayer-cdn.tcgplayer.com/product/98184_200w.jpg",
      "modifiedOn": "2022-12-16T15:59:24.603",
      "name": "Fairy Energy (#9)",
      "presaleInfo": {
        "isPresale": false,
        "note": null,
        "releasedOn": null
      },
      "productId": 98184,
      "url": "https://www.tcgplayer.com/product/98184/pokemon-xy-trainer-kit-bisharp-and-wigglytuff-fairy-energy-9"
    },
    {
      "categoryId": 3,
      "cleanName": "Fairy Energy 10",
      "extendedData": [
        {
          "displayName": "Card Number",
          "name": "Number",
          "value": "10/30"
        },
        {
          "displayName": "Rarity",
          "name": "Rarity",
          "value": "Common"
        },
        {
          "displayName": "Card Type",
          "name": "Card Type",
          "value": "Basic Energy"
        }
      ],
      "groupId": 1533,
      "imageCount": 0,
      "imageUrl": "https://tcgplayer-cdn.tcgplayer.com/product/98185_200w.jpg",
      "modifiedOn": "2022-12-16T15:59:34.967",
      "name": "Fairy Energy (#10)",
      "presaleInfo": {
        "isPresale": false,
        "note": null,
        "releasedOn": null
      },
      "productId": 98185,
      "url": "https://www.tcgplayer.com/product/98185/pokemon-xy-trainer-kit-bisharp-and-wigglytuff-fairy-energy-10"
    },
    {
      "categoryId": 3,
      "cleanName": "Fairy Energy 17",
      "extendedData": [
        {
          "displayName": "Card Number",
          "name": "Number",
          "value": "17/30"
        },
        {
          "displayName": "Rarity",
          "name": "Rarity",
          "value": "Common"
        },
        {
          "displayName": "Card Type",
          "name": "Card Type",
          "value": "Basic Energy"
        }
      ],
      "groupId": 1533,
      "imageCount": 0,
      "imageUrl": "https://tcgplayer-cdn.tcgplayer.com/product/98186_200w.jpg",
      "modifiedOn": "2022-12-16T16:10:51.187",
      "name": "Fairy Energy (#17)",
      "presaleInfo": {
        "isPresale": false,
        "note": null,
        "releasedOn": null
      },
      "productId": 98186,
      "url": "https://www.tcgplayer.com/product/98186/pokemon-xy-trainer-kit-bisharp-and-wigglytuff-fairy-energy-17"
    },
    {
      "categoryId": 3,
      "cleanName": "Fairy Energy 21",
      "extendedData": [
        {
          "displayName": "Card Number",
          "name": "Number",
          "value": "21/30"
        },
        {
          "displayName": "Rarity",
          "name": "Rarity",
          "value": "Common"
        },
        {
          "displayName": "Card Type",
          "name": "Card Type",
          "value": "Basic Energy"
        }
      ],
      "groupId": 1533,
      "imageCount": 0,
      "imageUrl": "https://tcgplayer-cdn.tcgplayer.com/product/98187_200w.jpg",
      "modifiedOn": "2022-12-16T16:12:38.607",
      "name": "Fairy Energy (#21)",
      "presaleInfo": {
        "isPresale": false,
        "note": null,
        "releasedOn": null
      },
      "productId": 98187,
      "url": "https://www.tcgplayer.com/product/98187/pokemon-xy-trainer-kit-bisharp-and-wigglytuff-fairy-energy-21"
    },
    {
      "categoryId": 3,
      "cleanName": "Fairy Energy 22",
      "extendedData": [
        {
          "displayName": "Card Number",
          "name": "Number",
          "value": "22/30"
        },
        {
          "displayName": "Rarity",
          "name": "Rarity",
          "value": "Common"
        },
        {
          "displayName": "Card Type",
          "name": "Card Type",
          "value": "Basic Energy"
        }
      ],
      "groupId": 1533,
      "imageCount": 0,
      "imageUrl": "https://tcgplayer-cdn.tcgplayer.com/product/98188_200w.jpg",
      "modifiedOn": "2022-12-16T16:12:54.963",
      "name": "Fairy Energy (#22)",
      "presaleInfo": {
        "isPresale": false,
        "note": null,
        "releasedOn": null
      },
      "productId": 98188,
      "url": "https://www.tcgplayer.com/product/98188/pokemon-xy-trainer-kit-bisharp-and-wigglytuff-fairy-energy-22"
    },
    {
      "categoryId": 3,
      "cleanName": "Fairy Energy 27",
      "extendedData": [
        {
          "displayName": "Card Number",
          "name": "Number",
          "value": "27/30"
        },
        {
          "displayName": "Rarity",
          "name": "Rarity",
          "value": "Common"
        },
        {
          "displayName": "Card Type",
          "name": "Card Type",
          "value": "Basic Energy"
        }
      ],
      "groupId": 1533,
      "imageCount": 0,
      "imageUrl": "https://tcgplayer-cdn.tcgplayer.com/product/98189_200w.jpg",
      "modifiedOn": "2022-12-16T16:14:12.307",
      "name": "Fairy Energy (#27)",
      "presaleInfo": {
        "isPresale": false,
        "note": null,
        "releasedOn": null
      },
      "productId": 98189,
      "url": "https://www.tcgplayer.com/product/98189/pokemon-xy-trainer-kit-bisharp-and-wigglytuff-fairy-energy-27"
    },
    {
      "categoryId": 3,
      "cleanName": "Sentret",
      "extendedData": [
        {
          "displayName": "Card Number",
          "name": "Number",
          "value": "4/30"
        },
        {
          "displayName": "Rarity",
          "name": "Rarity",
          "value": "Common"
        },
        {
          "displayName": "Card Type",
          "name": "Card Type",
          "value": "Colorless"
        },
        {
          "displayName": "HP",
          "name": "HP",
          "value": "50"
        },
        {
          "displayName": "Stage",
          "name": "Stage",
          "value": "Basic"
        },
        {
          "displayName": "Attack 1",
          "name": "Attack 1",
          "value": "[1] Scratch (10)"
        },
        {
          "displayName": "Attack 2",
          "name": "Attack 2",
          "value": "[2] Tail Smack (20)"
        },
        {
          "displayName": "Weakness",
          "name": "Weakness",
          "value": "Fx2"
        },
        {
          "displayName": "Resistance",
          "name": "Resistance",
          "value": "None"
        },
        {
          "displayName": "Retreat Cost",
          "name": "RetreatCost",
          "value": "1"
        }
      ],
      "groupId": 1533,
      "imageCount": 0,
      "imageUrl": "https://tcgplayer-cdn.tcgplayer.com/product/98190_200w.jpg",
      "modifiedOn": "2022-12-16T15:57:32.79",
      "name": "Sentret",
      "presaleInfo": {
        "isPresale": false,
        "note": null,
        "releasedOn": null
      },
      "productId": 98190,
      "url": "https://www.tcgplayer.com/product/98190/pokemon-xy-trainer-kit-bisharp-and-wigglytuff-sentret"
    },
    {
      "categoryId": 3,
      "cleanName": "Pidgey 11",
      "extendedData": [
        {
          "displayName": "Card Number",
          "name": "Number",
          "value": "11/30"
        },
        {
          "displayName": "Rarity",
          "name": "Rarity",
          "value": "Common"
        },
        {
          "displayName": "Card Type",
          "name": "Card Type",
          "value": "Colorless"
        },
        {
          "displayName": "HP",
          "name": "HP",
          "value": "60"
        },
        {
          "displayName": "Stage",
          "name": "Stage",
          "value": "Basic"
        },
        {
          "displayName": "Attack 1",
          "name": "Attack 1",
          "value": "[1] Peck Off (10)\r\n\u003cbr\u003eBefore doing damage, discard all Pokemon Tool cards attached to your opponent's Active Pokemon."
        },
        {
          "displayName": "Weakness",
          "name": "Weakness",
          "value": "Lx2"
        },
        {
          "displayName": "Resistance",
          "name": "Resistance",
          "value": "F-20"
        },
        {
          "displayName": "Retreat Cost",
          "name": "RetreatCost",
          "value": "1"
        }
      ],
      "groupId": 1533,
      "imageCount": 0,
      "imageUrl": "https://tcgplayer-cdn.tcgplayer.com/product/98191_200w.jpg",
      "modifiedOn": "2022-12-16T16:00:48.683",
      "name": "Pidgey (#11)",
      "presaleInfo": {
        "isPresale": false,
        "note": null,
        "releasedOn": null
      },
      "productId": 98191,
      "url": "https://www.tcgplayer.com/product/98191/pokemon-xy-trainer-kit-bisharp-and-wigglytuff-pidgey-11"
    },
    {
      "categoryId": 3,
      "cleanName": "Jigglypuff 12",
      "extendedData": [
        {
          "displayName": "Card Number",
          "name": "Number",
          "value": "12/30"
        },
        {
          "displayName": "Rarity",
          "name": "Rarity",
          "value": "Common"
        },
        {
          "displayName": "Card Type",
          "name": "Card Type",
          "value": "Fairy"
        },
        {
          "displayName": "HP",
          "name": "HP",
          "value": "60"
        },
        {
          "displayName": "Stage",
          "name": "Stage",
          "value": "Basic"
        },
        {
          "displayName": "Attack 1",
          "name": "Attack 1",
          "value": "[1] Rollout (10)"
        },
        {
          "displayName": "Attack 2",
          "name": "Attack 2",
          "value": "[Y] Heartfelt Song\r\n\u003cbr\u003eDiscard a Darkness Energy attached to your opponent's Active Pokemon."
        },
        {
          "displayName": "Weakness",
          "name": "Weakness",
          "value": "Mx2"
        },
        {
          "displayName": "Resistance",
          "name": "Resistance",
          "value": "D-20"
        },
        {
          "displayName": "Retreat Cost",
          "name": "RetreatCost",
          "value": "1"
        }
      ],
      "groupId": 1533,
      "imageCount": 0,
      "imageUrl": "https://tcgplayer-cdn.tcgplayer.com/product/98192_200w.jpg",
      "modifiedOn": "2022-12-16T16:01:15.237",
      "name": "Jigglypuff (#12)",
      "presaleInfo": {
        "isPresale": false,
        "note": null,
        "releasedOn": null
      },
      "productId": 98192,
      "url": "https://www.tcgplayer.com/product/98192/pokemon-xy-trainer-kit-bisharp-and-wigglytuff-jigglypuff-12"
    },
    {
      "categoryId": 3,
      "cleanName": "Clefairy 13",
      "extendedData": [
        {
          "displayName": "Card Number",
          "name": "Number",
          "value": "13/30"
        },
        {
          "displayName": "Rarity",
          "name": "Rarity",
          "value": "Common"
        },
        {
          "displayName": "Card Type",
          "name": "Card Type",
          "value": "Fairy"
        },
        {
          "displayName": "HP",
          "name": "HP",
          "value": "60"
        },
        {
          "displayName": "Stage",
          "name": "Stage",
          "value": "Basic"
        },
        {
          "displayName": "Attack 1",
          "name": "Attack 1",
          "value": "[1] Moonlight\r\n\u003cbr\u003eHeal 30 damage from this Pokemon."
        },
        {
          "displayName": "Attack 2",
          "name": "Attack 2",
          "value": "[1Y] Pound (20)"
        },
        {
          "displayName": "Weakness",
          "name": "Weakness",
          "value": "Mx2"
        },
        {
          "displayName": "Resistance",
          "name": "Resistance",
          "value": "D-20"
        },
        {
          "displayName": "Retreat Cost",
          "name": "RetreatCost",
          "value": "1"
        }
      ],
      "groupId": 1533,
      "imageCount": 0,
      "imageUrl": "https://tcgplayer-cdn.tcgplayer.com/product/98193_200w.jpg",
      "modifiedOn": "2022-12-16T16:12:31.107",
      "name": "Clefairy (#13)",
      "presaleInfo": {
        "isPresale": false,
        "note": null,
        "releasedOn": null
      },
      "productId": 98193,
      "url": "https://www.tcgplayer.com/product/98193/pokemon-xy-trainer-kit-bisharp-and-wigglytuff-clefairy-13"
    },
    {
      "categoryId": 3,
      "cleanName": "Wigglytuff 14 Non Holo",
      "extendedData": [
        {
          "displayName": "Card Number",
          "name": "Number",
          "value": "14/30"
        },
        {
          "displayName": "Rarity",
          "name": "Rarity",
          "value": "Common"
        },
        {
          "displayName": "Card Type",
          "name": "Card Type",
          "value": "Fairy"
        },
        {
          "displayName": "HP",
          "name": "HP",
          "value": "100"
        },
        {
          "displayName": "Stage",
          "name": "Stage",
          "value": "Stage 1"
        },
        {
          "displayName": "Attack 1",
          "name": "Attack 1",
          "value": "[1] Balloon Barrage (20x)\r\n\u003cbr\u003eThis attack does 20 damage times the amount of Energy attached to this Pokemon."
        },
        {
          "displayName": "Attack 2",
          "name": "Attack 2",
          "value": "[1YY] Double-Edge (90)\r\n\u003cbr\u003eThis Pokemon does 10 damage to itself."
        },
        {
          "displayName": "Weakness",
          "name": "Weakness",
          "value": "Mx2"
        },
        {
          "displayName": "Resistance",
          "name": "Resistance",
          "value": "D-20"
        },
        {
          "displayName": "Retreat Cost",
          "name": "RetreatCost",
          "value": "2"
        }
      ],
      "groupId": 1533,
      "imageCount": 0,
      "imageUrl": "https://tcgplayer-cdn.tcgplayer.com/product/98194_200w.jpg",
      "modifiedOn": "2022-12-16T16:10:09.883",
      "name": "Wigglytuff (#14 Non-Holo)",
      "presaleInfo": {
        "isPresale": false,
        "note": null,
        "releasedOn": null
      },
      "productId": 98194,
      "url": "https://www.tcgplayer.com/product/98194/pokemon-xy-trainer-kit-bisharp-and-wigglytuff-wigglytuff-14-non-holo"
    },
    {
      "categoryId": 3,
      "cleanName": "Clefable 16",
      "extendedData": [
        {
          "displayName": "Card Number",
          "name": "Number",
          "value": "16/30"
        },
        {
          "displayName": "Rarity",
          "name": "Rarity",
          "value": "Common"
        },
        {
          "displayName": "Card Type",
          "name": "Card Type",
          "value": "Fairy"
        },
        {
          "displayName": "HP",
          "name": "HP",
          "value": "90"
        },
        {
          "displayName": "Stage",
          "name": "Stage",
          "value": "Stage 1"
        },
        {
          "displayName": "Attack 1",
          "name": "Attack 1",
          "value": "[1] Follow Me\r\n\u003cbr\u003eSwitch 1 of your opponent's Benched Pokemon with your opponent's Active Pokemon."
        },
        {
          "displayName": "Attack 2",
          "name": "Attack 2",
          "value": "[1Y] Moonblast (30)\r\n\u003cbr\u003eDuring your opponent's next turn, any damage done by attacks from the Defending Pokemon is reduced by 30 \u003ci\u003e(before applying Weakness and Resistance).\u003c/i\u003e"
        },
        {
          "displayName": "Weakness",
          "name": "Weakness",
          "value": "Mx2"
        },
        {
          "displayName": "Resistance",
          "name": "Resistance",
          "value": "D-20"
        },
        {
          "displayName": "Retreat Cost",
          "name": "RetreatCost",
          "value": "1"
        }
      ],
      "groupId": 1533,
      "imageCount": 0,
      "imageUrl": "https://tcgplayer-cdn.tcgplayer.com/product/98195_200w.jpg",
      "modifiedOn": "2022-12-16T16:10:43.717",
      "name": "Clefable (#16)",
      "presaleInfo": {
        "isPresale": false,
        "note": null,
        "releasedOn": null
      },
      "productId": 98195,
      "url": "https://www.tcgplayer.com/product/98195/pokemon-xy-trainer-kit-bisharp-and-wigglytuff-clefable-16"
    },
    {
      "categoryId": 3,
      "cleanName": "Potion 15 Wigglytuff",
      "extendedData": [
        {
          "displayName": "Card Number",
          "name": "Number",
          "value": "15/30"
        },
        {
          "displayName": "Rarity",
          "name": "Rarity",
          "value": "Common"
        },
        {
          "displayName": "Card Type",
          "name": "Card Type",
          "value": "Item"
        },
        {
          "displayName": "Card Text",
          "name": "CardText",
          "value": "Heal 30 damage from 1 of your Pokemon."
        }
      ],
      "groupId": 1533,
      "imageCount": 0,
      "imageUrl": "https://tcgplayer-cdn.tcgplayer.com/product/98196_200w.jpg",
      "modifiedOn": "2022-12-16T16:10:20.667",
      "name": "Potion (#15 - Wigglytuff)",
      "presaleInfo": {
        "isPresale": false,
        "note": null,
        "releasedOn": null
      },
      "productId": 98196,
      "url": "https://www.tcgplayer.com/product/98196/pokemon-xy-trainer-kit-bisharp-and-wigglytuff-potion-15-wigglytuff"
    },
    {
      "categoryId": 3,
      "cleanName": "Potion 20 Wigglytuff",
      "extendedData": [
        {
          "displayName": "Card Number",
          "name": "Number",
          "value": "20/30"
        },
        {
          "displayName": "Rarity",
          "name": "Rarity",
          "value": "Common"
        },
        {
          "displayName": "Card Type",
          "name": "Card Type",
          "value": "Item"
        },
        {
          "displayName": "Card Text",
          "name": "CardText",
          "value": "Heal 30 damage from 1 of your Pokemon."
        }
      ],
      "groupId": 1533,
      "imageCount": 0,
      "imageUrl": "https://tcgplayer-cdn.tcgplayer.com/product/98197_200w.jpg",
      "modifiedOn": "2022-12-16T16:11:41.393",
      "name": "Potion (#20 - Wigglytuff)",
      "presaleInfo": {
        "isPresale": false,
        "note": null,
        "releasedOn": null
      },
      "productId": 98197,
      "url": "https://www.tcgplayer.com/product/98197/pokemon-xy-trainer-kit-bisharp-and-wigglytuff-potion-20-wigglytuff"
    },
    {
      "categoryId": 3,
      "cleanName": "Swirlix 18",
      "extendedData": [
        {
          "displayName": "Card Number",
          "name": "Number",
          "value": "18/30"
        },
        {
          "displayName": "Rarity",
          "name": "Rarity",
          "value": "Common"
        },
        {
          "displayName": "Card Type",
          "name": "Card Type",
          "value": "Fairy"
        },
        {
          "displayName": "HP",
          "name": "HP",
          "value": "60"
        },
        {
          "displayName": "Stage",
          "name": "Stage",
          "value": "Basic"
        },
        {
          "displayName": "Attack 1",
          "name": "Attack 1",
          "value": "[Y] Draining Kiss (10)\r\n\u003cbr\u003eHeal 10 damage from this Pokemon."
        },
        {
          "displayName": "Weakness",
          "name": "Weakness",
          "value": "Mx2"
        },
        {
          "displayName": "Resistance",
          "name": "Resistance",
          "value": "D-20"
        },
        {
          "displayName": "Retreat Cost",
          "name": "RetreatCost",
          "value": "1"
        }
      ],
      "groupId": 1533,
      "imageCount": 0,
      "imageUrl": "https://tcgplayer-cdn.tcgplayer.com/product/98198_200w.jpg",
      "modifiedOn": "2022-12-16T16:11:17.603",
      "name": "Swirlix (#18)",
      "presaleInfo": {
        "isPresale": false,
        "note": null,
        "releasedOn": null
      },
      "productId": 98198,
      "url": "https://www.tcgplayer.com/product/98198/pokemon-xy-trainer-kit-bisharp-and-wigglytuff-swirlix-18"
    },
    {
      "categoryId": 3,
      "cleanName": "Clefairy 19",
      "extendedData": [
        {
          "displayName": "Card Number",
          "name": "Number",
          "value": "19/30"
        },
        {
          "displayName": "Rarity",
          "name": "Rarity",
          "value": "Common"
        },
        {
          "displayName": "Card Type",
          "name": "Card Type",
          "value": "Fairy"
        },
        {
          "displayName": "HP",
          "name": "HP",
          "value": "60"
        },
        {
          "displayName": "Stage",
          "name": "Stage",
          "value": "Basic"
        },
        {
          "displayName": "Attack 1",
          "name": "Attack 1",
          "value": "[1] Moonlight\r\n\u003cbr\u003eHeal 30 damage from this Pokemon."
        },
        {
          "displayName": "Attack 2",
          "name": "Attack 2",
          "value": "[1Y] Pound (20)"
        },
        {
          "displayName": "Weakness",
          "name": "Weakness",
          "value": "Mx2"
        },
        {
          "displayName": "Resistance",
          "name": "Resistance",
          "value": "D-20"
        },
        {
          "displayName": "Retreat Cost",
          "name": "RetreatCost",
          "value": "1"
        }
      ],
      "groupId": 1533,
      "imageCount": 0,
      "imageUrl": "https://tcgplayer-cdn.tcgplayer.com/product/98199_200w.jpg",
      "modifiedOn": "2022-12-16T16:11:26.493",
      "name": "Clefairy (#19)",
      "presaleInfo": {
        "isPresale": false,
        "note": null,
        "releasedOn": null
      },
      "productId": 98199,
      "url": "https://www.tcgplayer.com/product/98199/pokemon-xy-trainer-kit-bisharp-and-wigglytuff-clefairy-19"
    },
    {
      "categoryId": 3,
      "cleanName": "Pidgeotto 23",
      "extendedData": [
        {
          "displayName": "Card Number",
          "name": "Number",
          "value": "23/30"
        },
        {
          "displayName": "Rarity",
          "name": "Rarity",
          "value": "Common"
        },
        {
          "displayName": "Card Type",
          "name": "Card Type",
          "value": "Colorless"
        },
        {
          "displayName": "HP",
          "name": "HP",
          "value": "80"
        },
        {
          "displayName": "Stage",
          "name": "Stage",
          "value": "Stage 1"
        },
        {
          "displayName": "Attack 1",
          "name": "Attack 1",
          "value": "[1] Sand Attack \r\n\u003cbr\u003eIf the Defending Pokemon tries to attack during your opponent's next turn, your opponent flips a coin. If tails, that attack does nothing."
        },
        {
          "displayName": "Attack 2",
          "name": "Attack 2",
          "value": "[2] Ambush (20+)\r\n\u003cbr\u003eFlip a coin. If heads, this attack does 20 more damage."
        },
        {
          "displayName": "Weakness",
          "name": "Weakness",
          "value": "Lx2"
        },
        {
          "displayName": "Resistance",
          "name": "Resistance",
          "value": "F-20"
        },
        {
          "displayName": "Retreat Cost",
          "name": "RetreatCost",
          "value": "1"
        }
      ],
      "groupId": 1533,
      "imageCount": 0,
      "imageUrl": "https://tcgplayer-cdn.tcgplayer.com/product/98200_200w.jpg",
      "modifiedOn": "2022-12-16T16:13:18.1",
      "name": "Pidgeotto (#23)",
      "presaleInfo": {
        "isPresale": false,
        "note": null,
        "releasedOn": null
      },
      "productId": 98200,
      "url": "https://www.tcgplayer.com/product/98200/pokemon-xy-trainer-kit-bisharp-and-wigglytuff-pidgeotto-23"
    },
    {
      "categoryId": 3,
      "cleanName": "Trevor Wigglytuff",
      "extendedData": [
        {
          "displayName": "Card Number",
          "name": "Number",
          "value": "24/30"
        },
        {
          "displayName": "Rarity",
          "name": "Rarity",
          "value": "Common"
        },
        {
          "displayName": "Card Type",
          "name": "Card Type",
          "value": "Supporter"
        },
        {
          "displayName": "Card Text",
          "name": "CardText",
          "value": "Search your deck for a Pokemon, reveal it, and put it into your hand. Shuffle your deck afterward."
        }
      ],
      "groupId": 1533,
      "imageCount": 1,
      "imageUrl": "https://tcgplayer-cdn.tcgplayer.com/product/98201_200w.jpg",
      "modifiedOn": "2022-12-16T16:13:33.627",
      "name": "Trevor (Wigglytuff)",
      "presaleInfo": {
        "isPresale": false,
        "note": null,
        "releasedOn": null
      },
      "productId": 98201,
      "url": "https://www.tcgplayer.com/product/98201/pokemon-xy-trainer-kit-bisharp-and-wigglytuff-trevor-wigglytuff"
    },
    {
      "categoryId": 3,
      "cleanName": "Jigglypuff 25",
      "extendedData": [
        {
          "displayName": "Card Number",
          "name": "Number",
          "value": "25/30"
        },
        {
          "displayName": "Rarity",
          "name": "Rarity",
          "value": "Common"
        },
        {
          "displayName": "Card Type",
          "name": "Card Type",
          "value": "Fairy"
        },
        {
          "displayName": "HP",
          "name": "HP",
          "value": "60"
        },
        {
          "displayName": "Stage",
          "name": "Stage",
          "value": "Basic"
        },
        {
          "displayName": "Attack 1",
          "name": "Attack 1",
          "value": "[1] Rollout (10)"
        },
        {
          "displayName": "Attack 2",
          "name": "Attack 2",
          "value": "[Y] Heartfelt Song\r\n\u003cbr\u003eDiscard a Darkness Energy attached to your opponent's Active Pokemon."
        },
        {
          "displayName": "Weakness",
          "name": "Weakness",
          "value": "Mx2"
        },
        {
          "displayName": "Resistance",
          "name": "Resistance",
          "value": "D-20"
        },
        {
          "displayName": "Retreat Cost",
          "name": "RetreatCost",
          "value": "1"
        }
      ],
      "groupId": 1533,
      "imageCount": 0,
      "imageUrl": "https://tcgplayer-cdn.tcgplayer.com/product/98202_200w.jpg",
      "modifiedOn": "2022-12-16T16:13:41.153",
      "name": "Jigglypuff (#25)",
      "presaleInfo": {
        "isPresale": false,
        "note": null,
        "releasedOn": null
      },
      "productId": 98202,
      "url": "https://www.tcgplayer.com/product/98202/pokemon-xy-trainer-kit-bisharp-and-wigglytuff-jigglypuff-25"
    },
    {
      "categoryId": 3,
      "cleanName": "Tierno Wigglytuff",
      "extendedData": [
        {
          "displayName": "Card Number",
          "name": "Number",
          "value": "26/30"
        },
        {
          "displayName": "Rarity",
          "name": "Rarity",
          "value": "Common"
        },
        {
          "displayName": "Card Type",
          "name": "Card Type",
          "value": "Supporter"
        },
        {
          "displayName": "Card Text",
          "name": "CardText",
          "value": "Draw 3 cards."
        }
      ],
      "groupId": 1533,
      "imageCount": 0,
      "imageUrl": "https://tcgplayer-cdn.tcgplayer.com/product/98203_200w.jpg",
      "modifiedOn": "2022-12-16T16:14:04.93",
      "name": "Tierno (Wigglytuff)",
      "presaleInfo": {
        "isPresale": false,
        "note": null,
        "releasedOn": null
      },
      "productId": 98203,
      "url": "https://www.tcgplayer.com/product/98203/pokemon-xy-trainer-kit-bisharp-and-wigglytuff-tierno-wigglytuff"
    },
    {
      "categoryId": 3,
      "cleanName": "Clefable 28",
      "extendedData": [
        {
          "displayName": "Card Number",
          "name": "Number",
          "value": "28/30"
        },
        {
          "displayName": "Rarity",
          "name": "Rarity",
          "value": "Common"
        },
        {
          "displayName": "Card Type",
          "name": "Card Type",
          "value": "Fairy"
        },
        {
          "displayName": "HP",
          "name": "HP",
          "value": "90"
        },
        {
          "displayName": "Stage",
          "name": "Stage",
          "value": "Stage 1"
        },
        {
          "displayName": "Attack 1",
          "name": "Attack 1",
          "value": "[1] Follow Me\r\n\u003cbr\u003eSwitch 1 of your opponent's Benched Pokemon with your opponent's Active Pokemon."
        },
        {
          "displayName": "Attack 2",
          "name": "Attack 2",
          "value": "[1Y] Moonblast (30)\r\n\u003cbr\u003eDuring your opponent's next turn, any damage done by attacks from the Defending Pokemon is reduced by 30 \u003ci\u003e(before applying Weakness and Resistance).\u003c/i\u003e"
        },
        {
          "displayName": "Weakness",
          "name": "Weakness",
          "value": "Mx2"
        },
        {
          "displayName": "Resistance",
          "name": "Resistance",
          "value": "D-20"
        },
        {
          "displayName": "Retreat Cost",
          "name": "RetreatCost",
          "value": "1"
        }
      ],
      "groupId": 1533,
      "imageCount": 0,
      "imageUrl": "https://tcgplayer-cdn.tcgplayer.com/product/98204_200w.jpg",
      "modifiedOn": "2022-12-16T16:14:28.097",
      "name": "Clefable (#28)",
      "presaleInfo": {
        "isPresale": false,
        "note": null,
        "releasedOn": null
      },
      "productId": 98204,
      "url": "https://www.tcgplayer.com/product/98204/pokemon-xy-trainer-kit-bisharp-and-wigglytuff-clefable-28"
    },
    {
      "categoryId": 3,
      "cleanName": "Pidgey 29",
      "extendedData": [
        {
          "displayName": "Card Number",
          "name": "Number",
          "value": "29/30"
        },
        {
          "displayName": "Rarity",
          "name": "Rarity",
          "value": "Common"
        },
        {
          "displayName": "Card Type",
          "name": "Card Type",
          "value": "Colorless"
        },
        {
          "displayName": "HP",
          "name": "HP",
          "value": "60"
        },
        {
          "displayName": "Stage",
          "name": "Stage",
          "value": "Basic"
        },
        {
          "displayName": "Attack 1",
          "name": "Attack 1",
          "value": "[1] Peck Off (10)\r\n\u003cbr\u003eBefore doing damage, discard all Pokemon Tool cards attached to your opponent's Active Pokemon."
        },
        {
          "displayName": "Weakness",
          "name": "Weakness",
          "value": "Lx2"
        },
        {
          "displayName": "Resistance",
          "name": "Resistance",
          "value": "F-20"
        },
        {
          "displayName": "Retreat Cost",
          "name": "RetreatCost",
          "value": "1"
        }
      ],
      "groupId": 1533,
      "imageCount": 0,
      "imageUrl": "https://tcgplayer-cdn.tcgplayer.com/product/98205_200w.jpg",
      "modifiedOn": "2022-12-16T16:14:42.723",
      "name": "Pidgey (#29)",
      "presaleInfo": {
        "isPresale": false,
        "note": null,
        "releasedOn": null
      },
      "productId": 98205,
      "url": "https://www.tcgplayer.com/product/98205/pokemon-xy-trainer-kit-bisharp-and-wigglytuff-pidgey-29"
    },
    {
      "categoryId": 3,
      "cleanName": "Wigglytuff 30 Holo",
      "extendedData": [
        {
          "displayName": "Card Number",
          "name": "Number",
          "value": "30/30"
        },
        {
          "displayName": "Rarity",
          "name": "Rarity",
          "value": "Common"
        },
        {
          "displayName": "Card Type",
          "name": "Card Type",
          "value": "Fairy"
        },
        {
          "displayName": "HP",
          "name": "HP",
          "value": "100"
        },
        {
          "displayName": "Stage",
          "name": "Stage",
          "value": "Stage 1"
        },
        {
          "displayName": "Attack 1",
          "name": "Attack 1",
          "value": "[1] Balloon Barrage (20x)\r\n\u003cbr\u003eThis attack does 20 damage times the amount of Energy attached to this Pokemon."
        },
        {
          "displayName": "Attack 2",
          "name": "Attack 2",
          "value": "[1YY] Double-Edge (90)\r\n\u003cbr\u003eThis Pokemon does 10 damage to itself."
        },
        {
          "displayName": "Weakness",
          "name": "Weakness",
          "value": "Mx2"
        },
        {
          "displayName": "Resistance",
          "name": "Resistance",
          "value": "D-20"
        },
        {
          "displayName": "Retreat Cost",
          "name": "RetreatCost",
          "value": "2"
        }
      ],
      "groupId": 1533,
      "imageCount": 0,
      "imageUrl": "https://tcgplayer-cdn.tcgplayer.com/product/98206_200w.jpg",
      "modifiedOn": "2022-12-16T16:15:05.23",
      "name": "Wigglytuff (#30 Holo)",
      "presaleInfo": {
        "isPresale": false,
        "note": null,
        "releasedOn": null
      },
      "productId": 98206,
      "url": "https://www.tcgplayer.com/product/98206/pokemon-xy-trainer-kit-bisharp-and-wigglytuff-wigglytuff-30-holo"
    },
    {
      "categoryId": 3,
      "cleanName": "Code Card XY Trainer Kit Bisharp and Wigglytuff",
      "extendedData": [
        {
          "displayName": "Rarity",
          "name": "Rarity",
          "value": "Code Card"
        },
        {
          "displayName": "Card Text",
          "name": "CardText",
          "value": "This listing is \u003cstrong\u003enot\u003c/strong\u003e a physical item. Please keep in mind that this \u003cstrong\u003eCode Card\u003c/strong\u003e listing represents a digital copy of the stated item for the Pokmon TCG Online \u003cstrong\u003eand/or\u003c/strong\u003e the Pokmon TCG Live games. You may receive the physical \u003cstrong\u003eCode Card\u003c/strong\u003e. Upon purchase, please work with your specific Seller by sending them a message using the \u003cstrong\u003eContact Seller\u003c/strong\u003e button on the order details in your \u003ca href=https://store.tcgplayer.com/myaccount/orderhistory\u003eOrder History\u003c/a\u003e to opt in to having your \u003cstrong\u003eCode Card\u003c/strong\u003e code delivered digitally due to the nature of the product."
        }
      ],
      "groupId": 1533,
      "imageCount": 1,
      "imageUrl": "https://tcgplayer-cdn.tcgplayer.com/product/283260_200w.jpg",
      "modifiedOn": "2023-03-31T16:31:12.98",
      "name": "Code Card - XY Trainer Kit: Bisharp \u0026 Wigglytuff",
      "presaleInfo": {
        "isPresale": false,
        "note": null,
        "releasedOn": null
      },
      "productId": 283260,
      "url": "https://www.tcgplayer.com/product/283260/pokemon-xy-trainer-kit-bisharp-and-wigglytuff-code-card-xy-trainer-kit-bisharp-and-wigglytuff"
    }
  ],
  "success": true,
  "totalItems": 62
}