{
  "errors": [],
  "results": [
    {
      "categoryId": 2,
      "cleanName": "Sage with Eyes of Blue UTR",
      "extendedData": [
        {
          "displayName": "Number",
          "name": "Number",
          "value": "OP27-EN001"
        },
        {
          "displayName": "Rarity",
          "name": "Rarity",
          "value": "Ultimate Rare"
        },
        {
          "displayName": "Attribute",
          "name": "Attribute",
          "value": "LIGHT"
        },
        {
          "displayName": "Monster Type",
          "name": "MonsterType",
          "value": "Spellcaster"
        },
        {
          "displayName": "Card Type",
          "name": "Card Type",
          "value": "Tuner/Effect Monster"
        },
        {
          "displayName": "Attack",
          "name": "Attack",
          "value": "0"
        },
        {
          "displayName": "Defense",
          "name": "Defense",
          "value": "1500"
        },
        {
          "displayName": "Description",
          "name": "Description",
          "value": "When this card is Normal Summoned: You can add 1 Level 1 LIGHT Tuner from your Deck to your hand, except \"Sage with Eyes of Blue\". You can discard this card, then target 1 Effect Monster you control; send it to the GY, and if you do, Special Summon 1 \"Blue-Eyes\" monster from your Deck. You can only use this effect of \"Sage with Eyes of Blue\" once per turn."
        }
      ],
      "groupId": 23786,
      "imageCount": 0,
      "imageUrl": "https://tcgplayer-cdn.tcgplayer.com/product/620245_200w.jpg",
      "modifiedOn": "2025-04-21T20:03:08.91",
      "name": "Sage with Eyes of Blue (UTR)",
      "presaleInfo": {
        "isPresale": false,
        "note": null,
        "releasedOn": null
      },
      "productId": 620245,
      "url": "https://www.tcgplayer.com/product/620245/yugioh-ots-tournament-pack-27-sage-with-eyes-of-blue-utr"
    },
    {
      "categoryId": 2,
      "cleanName": "Silhouhatte Rabbit UTR",
      "extendedData": [
        {
          "displayName": "Number",
          "name": "Number",
          "value": "OP27-EN002"
        },
        {
          "displayName": "Rarity",
          "name": "Rarity",
          "value": "Ultimate Rare"
        },
        {
          "displayName": "Attribute",
          "name": "Attribute",
          "value": "LIGHT"
        },
        {
          "displayName": "Monster Type",
          "name": "MonsterType",
          "value": "Illusion"
        },
        {
          "displayName": "Card Type",
          "name": "Card Type",
          "value": "Link/Effect Monster"
        },
        {
          "displayName": "Attack",
          "name": "Attack",
          "value": "1500"
        },
        {
          "displayName": "Description",
          "name": "Description",
          "value": "2 Effect Monsters\u003cbr\u003eIf this card battles a monster, neither can be destroyed by that battle. You can only use each of the following effects of \"Silhouhatte Rabbit\" once per turn. If this card is Link Summoned: You can Set 1 Continuous Trap from your Deck with an effect that Special Summons itself as a monster, also this card cannot be used as Link Material this turn. If a card in the Spell \u0026 Trap Zone is Special Summoned to the Monster Zone (except during the Damage Step): You can target 1 Spell/Trap your opponent controls; destroy it."
        },
        {
          "displayName": "Link Rating",
          "name": "LinkRating",
          "value": "2"
        },
        {
          "displayName": "Link Arrows",
          "name": "LinkArrows",
          "value": "Bottom-Right;Bottom-Left"
        }
      ],
      "groupId": 23786,
      "imageCount": 0,
      "imageUrl": "https://tcgplayer-cdn.tcgplayer.com/product/620246_200w.jpg",
      "modifiedOn": "2025-04-21T20:03:17.467",
      "name": "Silhouhatte Rabbit (UTR)",
      "presaleInfo": {
        "isPresale": false,
        "note": null,
        "releasedOn": null
      },
      "productId": 620246,
      "url": "https://www.tcgplayer.com/product/620246/yugioh-ots-tournament-pack-27-silhouhatte-rabbit-utr"
    },
    {
      "categoryId": 2,
      "cleanName": "Dark Fusion UTR",
      "extendedData": [
        {
          "displayName": "Number",
          "name": "Number",
          "value": "OP27-EN003"
        },
        {
          "displayName": "Rarity",
          "name": "Rarity",
          "value": "Ultimate Rare"
        },
        {
          "displayName": "Attribute",
          "name": "Attribute",
          "value": "SPELL"
        },
        {
          "displayName": "Card Type",
          "name": "Card Type",
          "value": "Normal Spell"
        },
        {
          "displayName": "Description",
          "name": "Description",
          "value": "Fusion Summon 1 Fiend Fusion Monster from your Extra Deck, using monsters from your hand or field as material. Your opponent cannot target it with card effects this turn."
        }
      ],
      "groupId": 23786,
      "imageCount": 0,
      "imageUrl": "https://tcgplayer-cdn.tcgplayer.com/product/620247_200w.jpg",
      "modifiedOn": "2025-04-21T20:02:59.213",
      "name": "Dark Fusion (UTR)",
      "presaleInfo": {
        "isPresale": false,
        "note": null,
        "releasedOn": null
      },
      "productId": 620247,
      "url": "https://www.tcgplayer.com/product/620247/yugioh-ots-tournament-pack-27-dark-fusion-utr"
    },
    {
      "categoryId": 2,
      "cleanName": "Ghostrick Doll",
      "extendedData": [
        {
          "displayName": "Number",
          "name": "Number",
          "value": "OP27-EN004"
        },
        {
          "displayName": "Rarity",
          "name": "Rarity",
          "value": "Super Rare"
        },
        {
          "displayName": "Attribute",
          "name": "Attribute",
          "value": "DARK"
        },
        {
          "displayName": "Monster Type",
          "name": "MonsterType",
          "value": "Spellcaster"
        },
        {
          "displayName": "Card Type",
          "name": "Card Type",
          "value": "Effect Monster"
        },
        {
          "displayName": "Attack",
          "name": "Attack",
          "value": "300"
        },
        {
          "displayName": "Defense",
          "name": "Defense",
          "value": "1200"
        },
        {
          "displayName": "Description",
          "name": "Description",
          "value": "Cannot be Normal Summoned, unless you control a \"Ghostrick\" monster. Once per turn: You can change this card to face-down Defense Position. If this card is flipped face-up: During the End Phase of this turn, change as many face-up monsters on the field as possible to face-down Defense Position, then you can Special Summon 1 \"Ghostrick\" monster from your Deck in face-down Defense Position, whose Level is less than or equal to the number of monsters flipped face-down by this effect."
        }
      ],
      "groupId": 23786,
      "imageCount": 0,
      "imageUrl": "https://tcgplayer-cdn.tcgplayer.com/product/620248_200w.jpg",
      "modifiedOn": "2025-02-27T17:11:48.26",
      "name": "Ghostrick Doll",
      "presaleInfo": {
        "isPresale": false,
        "note": null,
        "releasedOn": null
      },
      "productId": 620248,
      "url": "https://www.tcgplayer.com/product/620248/yugioh-ots-tournament-pack-27-ghostrick-doll"
    },
    {
      "categoryId": 2,
      "cleanName": "Endymion the Magistus of Mastery",
      "extendedData": [
        {
          "displayName": "Number",
          "name": "Number",
          "value": "OP27-EN005"
        },
        {
          "displayName": "Rarity",
          "name": "Rarity",
          "value": "Super Rare"
        },
        {
          "displayName": "Attribute",
          "name": "Attribute",
          "value": "WATER"
        },
        {
          "displayName": "Monster Type",
          "name": "MonsterType",
          "value": "Spellcaster"
        },
        {
          "displayName": "Card Type",
          "name": "Card Type",
          "value": "Effect Monster"
        },
        {
          "displayName": "Attack",
          "name": "Attack",
          "value": "1300"
        },
        {
          "displayName": "Defense",
          "name": "Defense",
          "value": "1700"
        },
        {
          "displayName": "Description",
          "name": "Description",
          "value": "You can target 1 \"Magistus\" monster you control; equip it with 1 \"Magistus\" monster from your Extra Deck. You can target 1 face-up Spell you control; destroy it, and if you do, draw 1 card, then place 1 card from your hand on the bottom of the Deck. You can only use each effect of \"Endymion, the Magistus of Mastery\" once per turn."
        }
      ],
      "groupId": 23786,
      "imageCount": 0,
      "imageUrl": "https://tcgplayer-cdn.tcgplayer.com/product/620249_200w.jpg",
      "modifiedOn": "2025-02-27T17:11:48.34",
      "name": "Endymion, the Magistus of Mastery",
      "presaleInfo": {
        "isPresale": false,
        "note": null,
        "releasedOn": null
      },
      "productId": 620249,
      "url": "https://www.tcgplayer.com/product/620249/yugioh-ots-tournament-pack-27-endymion-the-magistus-of-mastery"
    },
    {
      "categoryId": 2,
      "cleanName": "Tenpai Dragon Chundra",
      "extendedData": [
        {
          "displayName": "Number",
          "name": "Number",
          "value": "OP27-EN006"
        },
        {
          "displayName": "Rarity",
          "name": "Rarity",
          "value": "Super Rare"
        },
        {
          "displayName": "Attribute",
          "name": "Attribute",
          "value": "FIRE"
        },
        {
          "displayName": "Monster Type",
          "name": "MonsterType",
          "value": "Dragon"
        },
        {
          "displayName": "Card Type",
          "name": "Card Type",
          "value": "Tuner/Effect Monster"
        },
        {
          "displayName": "Attack",
          "name": "Attack",
          "value": "1500"
        },
        {
          "displayName": "Defense",
          "name": "Defense",
          "value": "1000"
        },
        {
          "displayName": "Description",
          "name": "Description",
          "value": "Once per turn, during the Battle Phase, you can (Quick Effect): Immediately after this effect resolves, Synchro Summon using this card you control. You can only use each of the following effects of \"Tenpai Dragon Chundra\" once per turn. If you control a FIRE Dragon monster: You can Special Summon this card from your hand. At the start of the Damage Step, if a monster battles: You can Special Summon 1 Level 4 or lower FIRE Dragon monster from your Deck, except \"Tenpai Dragon Chundra\"."
        }
      ],
      "groupId": 23786,
      "imageCount": 0,
      "imageUrl": "https://tcgplayer-cdn.tcgplayer.com/product/620250_200w.jpg",
      "modifiedOn": "2025-02-27T17:11:48.43",
      "name": "Tenpai Dragon Chundra",
      "presaleInfo": {
        "isPresale": false,
        "note": null,
        "releasedOn": null
      },
      "productId": 620250,
      "url": "https://www.tcgplayer.com/product/620250/yugioh-ots-tournament-pack-27-tenpai-dragon-chundra"
    },
    {
      "categoryId": 2,
      "cleanName": "Gruesome Grave Squirmer",
      "extendedData": [
        {
          "displayName": "Number",
          "name": "Number",
          "value": "OP27-EN007"
        },
        {
          "displayName": "Rarity",
          "name": "Rarity",
          "value": "Super Rare"
        },
        {
          "displayName": "Attribute",
          "name": "Attribute",
          "value": "DARK"
        },
        {
          "displayName": "Monster Type",
          "name": "MonsterType",
          "value": "Fiend"
        },
        {
          "displayName": "Card Type",
          "name": "Card Type",
          "value": "Effect Monster"
        },
        {
          "displayName": "Attack",
          "name": "Attack",
          "value": "0"
        },
        {
          "displayName": "Defense",
          "name": "Defense",
          "value": "0"
        },
        {
          "displayName": "Description",
          "name": "Description",
          "value": "If you control a Fiend monster (Quick Effect): You can Special Summon this card from your hand, then you can destroy 1 \"Yubel\", or 1 monster that mentions it, in your Monster Zone. You can banish this card from your GY; Special Summon 1 Fiend monster with 0 ATK/DEF from your hand or GY, except \"Gruesome Grave Squirmer\". You can only use each effect of \"Gruesome Grave Squirmer\" once per turn."
        }
      ],
      "groupId": 23786,
      "imageCount": 0,
      "imageUrl": "https://tcgplayer-cdn.tcgplayer.com/product/620251_200w.jpg",
      "modifiedOn": "2025-02-27T17:11:48.523",
      "name": "Gruesome Grave Squirmer",
      "presaleInfo": {
        "isPresale": false,
        "note": null,
        "releasedOn": null
      },
      "productId": 620251,
      "url": "https://www.tcgplayer.com/product/620251/yugioh-ots-tournament-pack-27-gruesome-grave-squirmer"
    },
    {
      "categoryId": 2,
      "cleanName": "Wightlord",
      "extendedData": [
        {
          "displayName": "Number",
          "name": "Number",
          "value": "OP27-EN008"
        },
        {
          "displayName": "Rarity",
          "name": "Rarity",
          "value": "Super Rare"
        },
        {
          "displayName": "Attribute",
          "name": "Attribute",
          "value": "LIGHT"
        },
        {
          "displayName": "Monster Type",
          "name": "MonsterType",
          "value": "Zombie"
        },
        {
          "displayName": "Card Type",
          "name": "Card Type",
          "value": "Effect Monster"
        },
        {
          "displayName": "Attack",
          "name": "Attack",
          "value": "300"
        },
        {
          "displayName": "Defense",
          "name": "Defense",
          "value": "200"
        },
        {
          "displayName": "Description",
          "name": "Description",
          "value": "This card's name becomes \"Skull Servant\" while in the GY. You can only use each of the following effects of \"Wightlord\" once per turn. If you have \"Skull Servant\" or \"King of the Skull Servants\" in your GY: You can send this card from your hand or field to the GY; send cards from the top of your Deck to the GY, up to the number of \"Skull Servant\" and \"King of the Skull Servants\" in your GY. You can banish this card from your GY, then target 1 \"Skull Servant\" or \"King of the Skull Servants\" in your GY; Special Summon it."
        }
      ],
      "groupId": 23786,
      "imageCount": 0,
      "imageUrl": "https://tcgplayer-cdn.tcgplayer.com/product/620252_200w.jpg",
      "modifiedOn": "2025-02-27T17:11:48.617",
      "name": "Wightlord",
      "presaleInfo": {
        "isPresale": false,
        "note": null,
        "releasedOn": null
      },
      "productId": 620252,
      "url": "https://www.tcgplayer.com/product/620252/yugioh-ots-tournament-pack-27-wightlord"
    },
    {
      "categoryId": 2,
      "cleanName": "Rucia of the White Forest",
      "extendedData": [
        {
          "displayName": "Number",
          "name": "Number",
          "value": "OP27-EN009"
        },
        {
          "displayName": "Rarity",
          "name": "Rarity",
          "value": "Super Rare"
        },
        {
          "displayName": "Attribute",
          "name": "Attribute",
          "value": "LIGHT"
        },
        {
          "displayName": "Monster Type",
          "name": "MonsterType",
          "value": "Spellcaster"
        },
        {
          "displayName": "Card Type",
          "name": "Card Type",
          "value": "Tuner/Effect Monster"
        },
        {
          "displayName": "Attack",
          "name": "Attack",
          "value": "800"
        },
        {
          "displayName": "Defense",
          "name": "Defense",
          "value": "1500"
        },
        {
          "displayName": "Description",
          "name": "Description",
          "value": "If you control a \"White Forest\" monster: You can Special Summon this card from your hand. You can send 1 Spell/Trap from your hand or field to the GY; draw 1 card. If this card is in your GY (Quick Effect): You can target 1 \"White Forest\" Synchro Monster you control or in your GY; return it to the Extra Deck, and if you do, Special Summon this card, but negate its effects. You can only use each effect of \"Rucia of the White Forest\" once per turn."
        }
      ],
      "groupId": 23786,
      "imageCount": 0,
      "imageUrl": "https://tcgplayer-cdn.tcgplayer.com/product/620253_200w.jpg",
      "modifiedOn": "2026-01-07T19:39:43.763",
      "name": "Rucia of the White Forest",
      "presaleInfo": {
        "isPresale": false,
        "note": null,
        "releasedOn": null
      },
      "productId": 620253,
      "url": "https://www.tcgplayer.com/product/620253/yugioh-ots-tournament-pack-27-rucia-of-the-white-forest"
    },
    {
      "categoryId": 2,
      "cleanName": "Number 104 Masquerade",
      "extendedData": [
        {
          "displayName": "Number",
          "name": "Number",
          "value": "OP27-EN010"
        },
        {
          "displayName": "Rarity",
          "name": "Rarity",
          "value": "Super Rare"
        },
        {
          "displayName": "Attribute",
          "name": "Attribute",
          "value": "LIGHT"
        },
        {
          "displayName": "Monster Type",
          "name": "MonsterType",
          "value": "Spellcaster"
        },
        {
          "displayName": "Card Type",
          "name": "Card Type",
          "value": "Xyz/Effect Monster"
        },
        {
          "displayName": "Attack",
          "name": "Attack",
          "value": "2700"
        },
        {
          "displayName": "Defense",
          "name": "Defense",
          "value": "1200"
        },
        {
          "displayName": "Description",
          "name": "Description",
          "value": "3 Level 4 monsters\u003cbr\u003eDuring the Battle Phase, When your opponent activates a monster effect (Quick Effect): You can detach 1 material from this card; negate the activation, and if you do, inflict 800 damage to your opponent. Once per turn, during your Main Phase: You can send the top card of your opponent's Deck to the GY."
        }
      ],
      "groupId": 23786,
      "imageCount": 0,
      "imageUrl": "https://tcgplayer-cdn.tcgplayer.com/product/620254_200w.jpg",
      "modifiedOn": "2026-01-08T14:27:20.313",
      "name": "Number 104: Masquerade",
      "presaleInfo": {
        "isPresale": false,
        "note": null,
        "releasedOn": null
      },
      "productId": 620254,
      "url": "https://www.tcgplayer.com/product/620254/yugioh-ots-tournament-pack-27-number-104-masquerade"
    },
    {
      "categoryId": 2,
      "cleanName": "Fiendsmiths Sequence",
      "extendedData": [
        {
          "displayName": "Number",
          "name": "Number",
          "value": "OP27-EN011"
        },
        {
          "displayName": "Rarity",
          "name": "Rarity",
          "value": "Super Rare"
        },
        {
          "displayName": "Attribute",
          "name": "Attribute",
          "value": "LIGHT"
        },
        {
          "displayName": "Monster Type",
          "name": "MonsterType",
          "value": "Fiend"
        },
        {
          "displayName": "Card Type",
          "name": "Card Type",
          "value": "Link/Effect Monster"
        },
        {
          "displayName": "Attack",
          "name": "Attack",
          "value": "1200"
        },
        {
          "displayName": "Description",
          "name": "Description",
          "value": "2 monsters, including a LIGHT Fiend monster\u003cbr\u003eDuring your Main Phase: You can Fusion Summon 1 Fiend Fusion Monster from your Extra Deck, by shuffling its materials from your GY into the Deck. You can target 1 LIGHT non-Link Fiend monster you control; equip this card from your field or GY to that monster you control as an Equip Spell with the following effect.\u003cbr\u003e• Your opponent cannot target the equipped monster with card effects.\u003cbr\u003eYou can only use each effect of \"Fiendsmith's Sequence\" once per turn."
        },
        {
          "displayName": "Link Rating",
          "name": "LinkRating",
          "value": "2"
        },
        {
          "displayName": "Link Arrows",
          "name": "LinkArrows",
          "value": "Bottom-Left;Bottom-Right"
        }
      ],
      "groupId": 23786,
      "imageCount": 0,
      "imageUrl": "https://tcgplayer-cdn.tcgplayer.com/product/620255_200w.jpg",
      "modifiedOn": "2025-02-27T17:11:48.913",
      "name": "Fiendsmith's Sequence",
      "presaleInfo": {
        "isPresale": false,
        "note": null,
        "releasedOn": null
      },
      "productId": 620255,
      "url": "https://www.tcgplayer.com/product/620255/yugioh-ots-tournament-pack-27-fiendsmiths-sequence"
    },
    {
      "categoryId": 2,
      "cleanName": "Simultaneous Equation Cannons",
      "extendedData": [
        {
          "displayName": "Number",
          "name": "Number",
          "value": "OP27-EN012"
        },
        {
          "displayName": "Rarity",
          "name": "Rarity",
          "value": "Super Rare"
        },
        {
          "displayName": "Attribute",
          "name": "Attribute",
          "value": "TRAP"
        },
        {
          "displayName": "Card Type",
          "name": "Card Type",
          "value": "Normal Trap"
        },
        {
          "displayName": "Description",
          "name": "Description",
          "value": "Banish 1 Fusion Monster and 2 Xyz Monsters with the same Rank from your Extra Deck, whose combined Level and Ranks equal the total number of cards in both players' hands and on the field, then you can apply this effect.\u003cbr\u003e• Return 2 of your banished monsters to the Extra Deck (1 Xyz and 1 Fusion) whose combined Level and Rank equal the Level or Rank of 1 face-up monster your opponent controls, then banish all cards they control."
        }
      ],
      "groupId": 23786,
      "imageCount": 0,
      "imageUrl": "https://tcgplayer-cdn.tcgplayer.com/product/620256_200w.jpg",
      "modifiedOn": "2025-02-27T17:11:49.027",
      "name": "Simultaneous Equation Cannons",
      "presaleInfo": {
        "isPresale": false,
        "note": null,
        "releasedOn": null
      },
      "productId": 620256,
      "url": "https://www.tcgplayer.com/product/620256/yugioh-ots-tournament-pack-27-simultaneous-equation-cannons"
    },
    {
      "categoryId": 2,
      "cleanName": "Performage Plushfire",
      "extendedData": [
        {
          "displayName": "Number",
          "name": "Number",
          "value": "OP27-EN013"
        },
        {
          "displayName": "Rarity",
          "name": "Rarity",
          "value": "Common"
        },
        {
          "displayName": "Attribute",
          "name": "Attribute",
          "value": "FIRE"
        },
        {
          "displayName": "Monster Type",
          "name": "MonsterType",
          "value": "Spellcaster"
        },
        {
          "displayName": "Card Type",
          "name": "Card Type",
          "value": "Pendulum/Effect Monster"
        },
        {
          "displayName": "Attack",
          "name": "Attack",
          "value": "1000"
        },
        {
          "displayName": "Defense",
          "name": "Defense",
          "value": "1000"
        },
        {
          "displayName": "Description",
          "name": "Description",
          "value": "\u003cstrong\u003ePendulum Effect\u003c/strong\u003e\u003cbr\u003e\r\n\u003cbr\u003eIf a face-up \"Performage\" monster(s) you control is destroyed by battle or card effect: You can Special Summon this card from your Pendulum Zone, then take 500 damage. You can only use this effect of \"Performage Plushfire\" once per turn.\u003cbr\u003e\r\n\u003cbr\u003e\u003cbr\u003e\r\n\u003cbr\u003e\u003cstrong\u003eMonster Effect\u003c/strong\u003e\u003cbr\u003e\r\n\u003cbr\u003eIf this card on the field is destroyed by battle or card effect: You can Special Summon 1 \"Performage\" monster from your hand or Deck, except \"Performage Plushfire\". You can only use this effect of \"Performage Plushfire\" once per turn."
        }
      ],
      "groupId": 23786,
      "imageCount": 0,
      "imageUrl": "https://tcgplayer-cdn.tcgplayer.com/product/620257_200w.jpg",
      "modifiedOn": "2026-01-08T14:13:42.423",
      "name": "Performage Plushfire",
      "presaleInfo": {
        "isPresale": false,
        "note": null,
        "releasedOn": null
      },
      "productId": 620257,
      "url": "https://www.tcgplayer.com/product/620257/yugioh-ots-tournament-pack-27-performage-plushfire"
    },
    {
      "categoryId": 2,
      "cleanName": "Speedroid Den Den Daiko Duke",
      "extendedData": [
        {
          "displayName": "Number",
          "name": "Number",
          "value": "OP27-EN014"
        },
        {
          "displayName": "Rarity",
          "name": "Rarity",
          "value": "Common"
        },
        {
          "displayName": "Attribute",
          "name": "Attribute",
          "value": "WIND"
        },
        {
          "displayName": "Monster Type",
          "name": "MonsterType",
          "value": "Machine"
        },
        {
          "displayName": "Card Type",
          "name": "Card Type",
          "value": "Tuner/Effect Monster"
        },
        {
          "displayName": "Attack",
          "name": "Attack",
          "value": "1000"
        },
        {
          "displayName": "Defense",
          "name": "Defense",
          "value": "1000"
        },
        {
          "displayName": "Description",
          "name": "Description",
          "value": "You can banish this card from your GY; Special Summon 1 \"Speedroid\" Tuner from your hand or GY, except \"Speedroid Den-Den Daiko Duke\". You can only use this effect of \"Speedroid Den-Den Daiko Duke\" once per turn."
        }
      ],
      "groupId": 23786,
      "imageCount": 0,
      "imageUrl": "https://tcgplayer-cdn.tcgplayer.com/product/620258_200w.jpg",
      "modifiedOn": "2026-01-07T20:59:56.76",
      "name": "Speedroid Den-Den Daiko Duke",
      "presaleInfo": {
        "isPresale": false,
        "note": null,
        "releasedOn": null
      },
      "productId": 620258,
      "url": "https://www.tcgplayer.com/product/620258/yugioh-ots-tournament-pack-27-speedroid-den-den-daiko-duke"
    },
    {
      "categoryId": 2,
      "cleanName": "Crystron Citree",
      "extendedData": [
        {
          "displayName": "Number",
          "name": "Number",
          "value": "OP27-EN015"
        },
        {
          "displayName": "Rarity",
          "name": "Rarity",
          "value": "Common"
        },
        {
          "displayName": "Attribute",
          "name": "Attribute",
          "value": "WATER"
        },
        {
          "displayName": "Monster Type",
          "name": "MonsterType",
          "value": "Machine"
        },
        {
          "displayName": "Card Type",
          "name": "Card Type",
          "value": "Tuner/Effect Monster"
        },
        {
          "displayName": "Attack",
          "name": "Attack",
          "value": "500"
        },
        {
          "displayName": "Defense",
          "name": "Defense",
          "value": "500"
        },
        {
          "displayName": "Description",
          "name": "Description",
          "value": "During your opponent's Main or Battle Phase (Quick Effect): You can target 1 non-Tuner in your GY; Special Summon it, but its effects are negated (if any), then immediately after this effect resolves, Synchro Summon 1 Machine Synchro Monster using only that monster and this card. These Synchro Materials are banished instead of being sent to the GY. You can only use this effect of \"Crystron Citree\" once per turn."
        }
      ],
      "groupId": 23786,
      "imageCount": 0,
      "imageUrl": "https://tcgplayer-cdn.tcgplayer.com/product/620259_200w.jpg",
      "modifiedOn": "2025-02-27T17:11:49.323",
      "name": "Crystron Citree",
      "presaleInfo": {
        "isPresale": false,
        "note": null,
        "releasedOn": null
      },
      "productId": 620259,
      "url": "https://www.tcgplayer.com/product/620259/yugioh-ots-tournament-pack-27-crystron-citree"
    },
    {
      "categoryId": 2,
      "cleanName": "Crystron Sulfefnir",
      "extendedData": [
        {
          "displayName": "Number",
          "name": "Number",
          "value": "OP27-EN016"
        },
        {
          "displayName": "Rarity",
          "name": "Rarity",
          "value": "Common"
        },
        {
          "displayName": "Attribute",
          "name": "Attribute",
          "value": "WATER"
        },
        {
          "displayName": "Monster Type",
          "name": "MonsterType",
          "value": "Machine"
        },
        {
          "displayName": "Card Type",
          "name": "Card Type",
          "value": "Effect Monster"
        },
        {
          "displayName": "Attack",
          "name": "Attack",
          "value": "2000"
        },
        {
          "displayName": "Defense",
          "name": "Defense",
          "value": "1500"
        },
        {
          "displayName": "Description",
          "name": "Description",
          "value": "If this card is in your hand or GY: You can discard 1 \"Crystron\" card, except \"Crystron Sulfefnir\"; Special Summon this card in Defense Position, then destroy 1 card you control. If this card on the field is destroyed by battle or card effect: You can Special Summon 1 \"Crystron\" monster from your Deck in Defense Position. You can only use each effect of \"Crystron Sulfefnir\" once per turn."
        }
      ],
      "groupId": 23786,
      "imageCount": 0,
      "imageUrl": "https://tcgplayer-cdn.tcgplayer.com/product/620260_200w.jpg",
      "modifiedOn": "2025-02-27T17:11:49.43",
      "name": "Crystron Sulfefnir",
      "presaleInfo": {
        "isPresale": false,
        "note": null,
        "releasedOn": null
      },
      "productId": 620260,
      "url": "https://www.tcgplayer.com/product/620260/yugioh-ots-tournament-pack-27-crystron-sulfefnir"
    },
    {
      "categoryId": 2,
      "cleanName": "Evil HERO Sinister Necrom",
      "extendedData": [
        {
          "displayName": "Number",
          "name": "Number",
          "value": "OP27-EN017"
        },
        {
          "displayName": "Rarity",
          "name": "Rarity",
          "value": "Common"
        },
        {
          "displayName": "Attribute",
          "name": "Attribute",
          "value": "DARK"
        },
        {
          "displayName": "Monster Type",
          "name": "MonsterType",
          "value": "Fiend"
        },
        {
          "displayName": "Card Type",
          "name": "Card Type",
          "value": "Effect Monster"
        },
        {
          "displayName": "Attack",
          "name": "Attack",
          "value": "1600"
        },
        {
          "displayName": "Defense",
          "name": "Defense",
          "value": "1800"
        },
        {
          "displayName": "Description",
          "name": "Description",
          "value": "You can banish this card from your GY; Special Summon 1 \"Evil HERO\" monster from your hand or Deck, except \"Evil HERO Sinister Necrom\". You can only use this effect of \"Evil HERO Sinister Necrom\" once per turn."
        }
      ],
      "groupId": 23786,
      "imageCount": 0,
      "imageUrl": "https://tcgplayer-cdn.tcgplayer.com/product/620261_200w.jpg",
      "modifiedOn": "2025-02-27T17:11:49.65",
      "name": "Evil HERO Sinister Necrom",
      "presaleInfo": {
        "isPresale": false,
        "note": null,
        "releasedOn": null
      },
      "productId": 620261,
      "url": "https://www.tcgplayer.com/product/620261/yugioh-ots-tournament-pack-27-evil-hero-sinister-necrom"
    },
    {
      "categoryId": 2,
      "cleanName": "Speedroid CarTurbo",
      "extendedData": [
        {
          "displayName": "Number",
          "name": "Number",
          "value": "OP27-EN018"
        },
        {
          "displayName": "Rarity",
          "name": "Rarity",
          "value": "Common"
        },
        {
          "displayName": "Attribute",
          "name": "Attribute",
          "value": "WIND"
        },
        {
          "displayName": "Monster Type",
          "name": "MonsterType",
          "value": "Machine"
        },
        {
          "displayName": "Card Type",
          "name": "Card Type",
          "value": "Tuner/Effect Monster"
        },
        {
          "displayName": "Attack",
          "name": "Attack",
          "value": "800"
        },
        {
          "displayName": "Defense",
          "name": "Defense",
          "value": "1200"
        },
        {
          "displayName": "Description",
          "name": "Description",
          "value": "If you control a WIND monster: You can Special Summon this card from your hand, also you cannot activate monster effects for the rest of this turn, except WIND monsters. You can banish this card and 1 \"Speedroid\" monster from your GY; all WIND monsters you currently control gain 800 ATK until the end of this turn. You can only use each effect of \"Speedroid CarTurbo\" once per turn."
        }
      ],
      "groupId": 23786,
      "imageCount": 0,
      "imageUrl": "https://tcgplayer-cdn.tcgplayer.com/product/620262_200w.jpg",
      "modifiedOn": "2026-01-07T20:59:58.217",
      "name": "Speedroid CarTurbo",
      "presaleInfo": {
        "isPresale": false,
        "note": null,
        "releasedOn": null
      },
      "productId": 620262,
      "url": "https://www.tcgplayer.com/product/620262/yugioh-ots-tournament-pack-27-speedroid-carturbo"
    },
    {
      "categoryId": 2,
      "cleanName": "Crowley the Magistus of Grimoires",
      "extendedData": [
        {
          "displayName": "Number",
          "name": "Number",
          "value": "OP27-EN019"
        },
        {
          "displayName": "Rarity",
          "name": "Rarity",
          "value": "Common"
        },
        {
          "displayName": "Attribute",
          "name": "Attribute",
          "value": "DARK"
        },
        {
          "displayName": "Monster Type",
          "name": "MonsterType",
          "value": "Spellcaster"
        },
        {
          "displayName": "Card Type",
          "name": "Card Type",
          "value": "Effect Monster"
        },
        {
          "displayName": "Attack",
          "name": "Attack",
          "value": "1800"
        },
        {
          "displayName": "Defense",
          "name": "Defense",
          "value": "1000"
        },
        {
          "displayName": "Description",
          "name": "Description",
          "value": "You can send 1 Spellcaster monster from your hand or face-up field to the GY; Special Summon this card from your hand. You can declare 1 Attribute; this card becomes that Attribute until the end of this turn. You can banish this card from your GY, then target 1 \"Magistus\" monster you control; equip it with 1 \"Magistus\" monster from your GY, except a Level 4 monster. You can only use each effect of \"Crowley, the Magistus of Grimoires\" once per turn."
        }
      ],
      "groupId": 23786,
      "imageCount": 0,
      "imageUrl": "https://tcgplayer-cdn.tcgplayer.com/product/620263_200w.jpg",
      "modifiedOn": "2025-02-27T17:11:49.927",
      "name": "Crowley, the Magistus of Grimoires",
      "presaleInfo": {
        "isPresale": false,
        "note": null,
        "releasedOn": null
      },
      "productId": 620263,
      "url": "https://www.tcgplayer.com/product/620263/yugioh-ots-tournament-pack-27-crowley-the-magistus-of-grimoires"
    },
    {
      "categoryId": 2,
      "cleanName": "Zoroa the Magistus of Flame",
      "extendedData": [
        {
          "displayName": "Number",
          "name": "Number",
          "value": "OP27-EN020"
        },
        {
          "displayName": "Rarity",
          "name": "Rarity",
          "value": "Common"
        },
        {
          "displayName": "Attribute",
          "name": "Attribute",
          "value": "FIRE"
        },
        {
          "displayName": "Monster Type",
          "name": "MonsterType",
          "value": "Spellcaster"
        },
        {
          "displayName": "Card Type",
          "name": "Card Type",
          "value": "Tuner/Effect Monster"
        },
        {
          "displayName": "Attack",
          "name": "Attack",
          "value": "1500"
        },
        {
          "displayName": "Defense",
          "name": "Defense",
          "value": "1500"
        },
        {
          "displayName": "Description",
          "name": "Description",
          "value": "You can target 1 \"Magistus\" monster you control; equip it with 1 \"Magistus\" monster from your Extra Deck. If this card becomes equipped with a \"Magistus\" Monster Card: You can Special Summon 1 Level 4 Spellcaster monster from your hand or GY in Defense Position, except \"Zoroa, the Magistus of Flame\", but its effects are negated. You can only use each effect of \"Zoroa, the Magistus of Flame\" once per turn."
        }
      ],
      "groupId": 23786,
      "imageCount": 0,
      "imageUrl": "https://tcgplayer-cdn.tcgplayer.com/product/620264_200w.jpg",
      "modifiedOn": "2026-01-02T18:26:24.96",
      "name": "Zoroa, the Magistus of Flame",
      "presaleInfo": {
        "isPresale": false,
        "note": null,
        "releasedOn": null
      },
      "productId": 620264,
      "url": "https://www.tcgplayer.com/product/620264/yugioh-ots-tournament-pack-27-zoroa-the-magistus-of-flame"
    },
    {
      "categoryId": 2,
      "cleanName": "Evil HERO Malicious Bane",
      "extendedData": [
        {
          "displayName": "Number",
          "name": "Number",
          "value": "OP27-EN021"
        },
        {
          "displayName": "Rarity",
          "name": "Rarity",
          "value": "Common"
        },
        {
          "displayName": "Attribute",
          "name": "Attribute",
          "value": "DARK"
        },
        {
          "displayName": "Monster Type",
          "name": "MonsterType",
          "value": "Fiend"
        },
        {
          "displayName": "Card Type",
          "name": "Card Type",
          "value": "Fusion/Effect Monster"
        },
        {
          "displayName": "Attack",
          "name": "Attack",
          "value": "3000"
        },
        {
          "displayName": "Defense",
          "name": "Defense",
          "value": "3000"
        },
        {
          "displayName": "Description",
          "name": "Description",
          "value": "1 \"Evil HERO\" monster + 1 Level 5 or higher monster\u003cbr\u003eMust be Special Summoned with \"Dark Fusion\". Cannot be destroyed by battle or card effects. During your Main Phase: You can destroy all monsters your opponent controls with ATK less than or equal to this card's, also this card gains 200 ATK for each monster destroyed this way, also you cannot declare an attack for the rest of this turn, except with \"HERO\" monsters. You can only use this effect of \"Evil HERO Malicious Bane\" once per turn."
        }
      ],
      "groupId": 23786,
      "imageCount": 0,
      "imageUrl": "https://tcgplayer-cdn.tcgplayer.com/product/620265_200w.jpg",
      "modifiedOn": "2025-02-27T17:11:50.193",
      "name": "Evil HERO Malicious Bane",
      "presaleInfo": {
        "isPresale": false,
        "note": null,
        "releasedOn": null
      },
      "productId": 620265,
      "url": "https://www.tcgplayer.com/product/620265/yugioh-ots-tournament-pack-27-evil-hero-malicious-bane"
    },
    {
      "categoryId": 2,
      "cleanName": "Mereologic Aggregator",
      "extendedData": [
        {
          "displayName": "Number",
          "name": "Number",
          "value": "OP27-EN022"
        },
        {
          "displayName": "Rarity",
          "name": "Rarity",
          "value": "Common"
        },
        {
          "displayName": "Attribute",
          "name": "Attribute",
          "value": "DARK"
        },
        {
          "displayName": "Monster Type",
          "name": "MonsterType",
          "value": "Cyberse"
        },
        {
          "displayName": "Card Type",
          "name": "Card Type",
          "value": "Xyz/Effect Monster"
        },
        {
          "displayName": "Attack",
          "name": "Attack",
          "value": "2600"
        },
        {
          "displayName": "Defense",
          "name": "Defense",
          "value": "3000"
        },
        {
          "displayName": "Description",
          "name": "Description",
          "value": "2+ Level 9 monsters\u003cbr\u003eIf this card is Xyz Summoned: You can send 1 monster from your Extra Deck to the GY. You can target monsters in your GY, up to the number of materials this card has; detach materials from this card equal to the number of those targets in the GY, and if you do, attach those targets to this card as material. If this card is sent to the GY: You can target 1 face-up card on the field; negate its effects until the end of this turn. You can only use each effect of \"Mereologic Aggregator\" once per turn."
        }
      ],
      "groupId": 23786,
      "imageCount": 0,
      "imageUrl": "https://tcgplayer-cdn.tcgplayer.com/product/620266_200w.jpg",
      "modifiedOn": "2026-01-08T14:24:32.46",
      "name": "Mereologic Aggregator",
      "presaleInfo": {
        "isPresale": false,
        "note": null,
        "releasedOn": null
      },
      "productId": 620266,
      "url": "https://www.tcgplayer.com/product/620266/yugioh-ots-tournament-pack-27-mereologic-aggregator"
    },
    {
      "categoryId": 2,
      "cleanName": "Speedroid Wheel",
      "extendedData": [
        {
          "displayName": "Number",
          "name": "Number",
          "value": "OP27-EN023"
        },
        {
          "displayName": "Rarity",
          "name": "Rarity",
          "value": "Common"
        },
        {
          "displayName": "Attribute",
          "name": "Attribute",
          "value": "SPELL"
        },
        {
          "displayName": "Card Type",
          "name": "Card Type",
          "value": "Quick-Play Spell"
        },
        {
          "displayName": "Description",
          "name": "Description",
          "value": "Discard 1 card; roll a six-sided die, then Special Summon, from your hand and/or Deck, 1 or 2 \"Speedroid\" monsters whose total Levels equal the result, but negate their effects. If you do not Special Summon, you lose LP equal to the result x 500. You can only activate 1 \"Speedroid Wheel\" per turn."
        }
      ],
      "groupId": 23786,
      "imageCount": 0,
      "imageUrl": "https://tcgplayer-cdn.tcgplayer.com/product/620267_200w.jpg",
      "modifiedOn": "2026-01-07T21:01:03.763",
      "name": "Speedroid Wheel",
      "presaleInfo": {
        "isPresale": false,
        "note": null,
        "releasedOn": null
      },
      "productId": 620267,
      "url": "https://www.tcgplayer.com/product/620267/yugioh-ots-tournament-pack-27-speedroid-wheel"
    },
    {
      "categoryId": 2,
      "cleanName": "Rare Metalmorph",
      "extendedData": [
        {
          "displayName": "Number",
          "name": "Number",
          "value": "OP27-EN024"
        },
        {
          "displayName": "Rarity",
          "name": "Rarity",
          "value": "Common"
        },
        {
          "displayName": "Attribute",
          "name": "Attribute",
          "value": "TRAP"
        },
        {
          "displayName": "Card Type",
          "name": "Card Type",
          "value": "Continuous Trap"
        },
        {
          "displayName": "Description",
          "name": "Description",
          "value": "Activate this card by targeting 1 Machine monster on the field; while this card is face-up on the field, that Machine monster gains 500 ATK, also negate the first Spell effect that targets that monster. When that monster leaves the field, destroy this card."
        }
      ],
      "groupId": 23786,
      "imageCount": 0,
      "imageUrl": "https://tcgplayer-cdn.tcgplayer.com/product/620268_200w.jpg",
      "modifiedOn": "2026-01-07T19:24:30.783",
      "name": "Rare Metalmorph",
      "presaleInfo": {
        "isPresale": false,
        "note": null,
        "releasedOn": null
      },
      "productId": 620268,
      "url": "https://www.tcgplayer.com/product/620268/yugioh-ots-tournament-pack-27-rare-metalmorph"
    },
    {
      "categoryId": 2,
      "cleanName": "Powersink Stone",
      "extendedData": [
        {
          "displayName": "Number",
          "name": "Number",
          "value": "OP27-EN025"
        },
        {
          "displayName": "Rarity",
          "name": "Rarity",
          "value": "Common"
        },
        {
          "displayName": "Attribute",
          "name": "Attribute",
          "value": "TRAP"
        },
        {
          "displayName": "Card Type",
          "name": "Card Type",
          "value": "Continuous Trap"
        },
        {
          "displayName": "Description",
          "name": "Description",
          "value": "Each time a monster effect is activated, place 1 Spellstone Counter on this card when that effect resolves (max. 2). While this card has 2 Spellstone Counters, neither player can activate the effects of face-up monsters on the field, also the effects of face-up monsters on the field are negated. Once per turn, during the End Phase, if this card has any Spellstone Counters: Remove them."
        }
      ],
      "groupId": 23786,
      "imageCount": 0,
      "imageUrl": "https://tcgplayer-cdn.tcgplayer.com/product/620269_200w.jpg",
      "modifiedOn": "2026-01-08T14:20:32.703",
      "name": "Powersink Stone",
      "presaleInfo": {
        "isPresale": false,
        "note": null,
        "releasedOn": null
      },
      "productId": 620269,
      "url": "https://www.tcgplayer.com/product/620269/yugioh-ots-tournament-pack-27-powersink-stone"
    },
    {
      "categoryId": 2,
      "cleanName": "Grinning Grave Virus",
      "extendedData": [
        {
          "displayName": "Number",
          "name": "Number",
          "value": "OP27-EN026"
        },
        {
          "displayName": "Rarity",
          "name": "Rarity",
          "value": "Common"
        },
        {
          "displayName": "Attribute",
          "name": "Attribute",
          "value": "TRAP"
        },
        {
          "displayName": "Card Type",
          "name": "Card Type",
          "value": "Normal Trap"
        },
        {
          "displayName": "Description",
          "name": "Description",
          "value": "Tribute 1 DARK monster with 3000 or less ATK; your opponent destroys 1 card (of their choice) in their hand or Deck for every 500 ATK that monster had on the field. If you Tributed a monster with 2000 or more ATK to activate this card, look at all cards your opponent draws until the end of their 3rd turn after this card resolves, and destroy all monsters among them. Cards destroyed and sent to the GY by this card's effects cannot activate their own effects that same turn."
        }
      ],
      "groupId": 23786,
      "imageCount": 0,
      "imageUrl": "https://tcgplayer-cdn.tcgplayer.com/product/620270_200w.jpg",
      "modifiedOn": "2026-01-07T15:20:19.077",
      "name": "Grinning Grave Virus",
      "presaleInfo": {
        "isPresale": false,
        "note": null,
        "releasedOn": null
      },
      "productId": 620270,
      "url": "https://www.tcgplayer.com/product/620270/yugioh-ots-tournament-pack-27-grinning-grave-virus"
    },
    {
      "categoryId": 2,
      "cleanName": "Black Sheep Token",
      "extendedData": [
        {
          "displayName": "Number",
          "name": "Number",
          "value": "OP27-EN027"
        },
        {
          "displayName": "Rarity",
          "name": "Rarity",
          "value": "Super Rare"
        },
        {
          "displayName": "Attribute",
          "name": "Attribute",
          "value": "DARK"
        },
        {
          "displayName": "Monster Type",
          "name": "MonsterType",
          "value": "Zombie"
        },
        {
          "displayName": "Card Type",
          "name": "Card Type",
          "value": "Normal Monster"
        },
        {
          "displayName": "Attack",
          "name": "Attack",
          "value": "0"
        },
        {
          "displayName": "Defense",
          "name": "Defense",
          "value": "0"
        },
        {
          "displayName": "Description",
          "name": "Description",
          "value": "This card can be used as a \"Black Sheep Token\".\u003cbr\u003e\u003cbr\u003e\u003cbr\u003e*If used for another Token, apply that Token's Type/Attribute/Level/ATK/DEF."
        }
      ],
      "groupId": 23786,
      "imageCount": 0,
      "imageUrl": "https://tcgplayer-cdn.tcgplayer.com/product/620271_200w.jpg",
      "modifiedOn": "2025-02-27T17:11:50.94",
      "name": "Black Sheep Token",
      "presaleInfo": {
        "isPresale": false,
        "note": null,
        "releasedOn": null
      },
      "productId": 620271,
      "url": "https://www.tcgplayer.com/product/620271/yugioh-ots-tournament-pack-27-black-sheep-token"
    }
  ],
  "success": true,
  "totalItems": 27
}